[{"title": "4 - Burton Wade (0001950582) (Reporting)", "filing_url": "https://www.sec.gov/Archives/edgar/data/1950582/000140810025000170/0001408100-25-000170-index.htm", "filing_date": "2025-11-03T18:27:26-05:00", "summary": "<b>Filed:</b> 2025-11-03 <b>AccNo:</b> 0001408100-25-000170 <b>Size:</b> 6 KB"}, {"title": "4 - Kennedy-Wilson Holdings, Inc. (0001408100) (Issuer)", "filing_url": "https://www.sec.gov/Archives/edgar/data/1408100/000140810025000170/0001408100-25-000170-index.htm", "filing_date": "2025-11-03T18:27:26-05:00", "summary": "<b>Filed:</b> 2025-11-03 <b>AccNo:</b> 0001408100-25-000170 <b>Size:</b> 6 KB"}, {"title": "4 - DeCecco Julie A. (0002012993) (Reporting)", "filing_url": "https://www.sec.gov/Archives/edgar/data/2012993/000201299325000005/0002012993-25-000005-index.htm", "filing_date": "2025-11-03T18:20:25-05:00", "summary": "<b>Filed:</b> 2025-11-03 <b>AccNo:</b> 0002012993-25-000005 <b>Size:</b> 8 KB"}, {"title": "4 - VAIL RESORTS INC (0000812011) (Issuer)", "filing_url": "https://www.sec.gov/Archives/edgar/data/812011/000201299325000005/0002012993-25-000005-index.htm", "filing_date": "2025-11-03T18:20:25-05:00", "summary": "<b>Filed:</b> 2025-11-03 <b>AccNo:</b> 0002012993-25-000005 <b>Size:</b> 8 KB"}, {"title": "4 - Brooks Bradford L. (0001738721) (Reporting)", "filing_url": "https://www.sec.gov/Archives/edgar/data/1738721/000173872125000004/0001738721-25-000004-index.htm", "filing_date": "2025-11-03T18:19:15-05:00", "summary": "<b>Filed:</b> 2025-11-03 <b>AccNo:</b> 0001738721-25-000004 <b>Size:</b> 4 KB"}, {"title": "4 - QUALYS, INC. (0001107843) (Issuer)", "filing_url": "https://www.sec.gov/Archives/edgar/data/1107843/000173872125000004/0001738721-25-000004-index.htm", "filing_date": "2025-11-03T18:19:15-05:00", "summary": "<b>Filed:</b> 2025-11-03 <b>AccNo:</b> 0001738721-25-000004 <b>Size:</b> 4 KB"}, {"title": "4 - Susan Scott Heyneman Trust, Susan Heyneman & First Interstate Wealth Management Co-Trustees (0001908880) (Reporting)", "filing_url": "https://www.sec.gov/Archives/edgar/data/1908880/000149315225020651/0001493152-25-020651-index.htm", "filing_date": "2025-11-03T18:18:58-05:00", "summary": "<b>Filed:</b> 2025-11-03 <b>AccNo:</b> 0001493152-25-020651 <b>Size:</b> 6 KB"}, {"title": "4 - FIRST INTERSTATE BANCSYSTEM INC (0000860413) (Issuer)", "filing_url": "https://www.sec.gov/Archives/edgar/data/860413/000149315225020651/0001493152-25-020651-index.htm", "filing_date": "2025-11-03T18:18:58-05:00", "summary": "<b>Filed:</b> 2025-11-03 <b>AccNo:</b> 0001493152-25-020651 <b>Size:</b> 6 KB"}, {"title": "4 - Keil Robert (0002010488) (Reporting)", "filing_url": "https://www.sec.gov/Archives/edgar/data/2010488/000201048825000003/0002010488-25-000003-index.htm", "filing_date": "2025-11-03T18:17:00-05:00", "summary": "<b>Filed:</b> 2025-11-03 <b>AccNo:</b> 0002010488-25-000003 <b>Size:</b> 4 KB"}, {"title": "4 - Finwise Bancorp (0001856365) (Issuer)", "filing_url": "https://www.sec.gov/Archives/edgar/data/1856365/000201048825000003/0002010488-25-000003-index.htm", "filing_date": "2025-11-03T18:17:00-05:00", "summary": "<b>Filed:</b> 2025-11-03 <b>AccNo:</b> 0002010488-25-000003 <b>Size:</b> 4 KB"}, {"title": "4 - SCHNABEL MICHAEL KORT (0001952244) (Reporting)", "filing_url": "https://www.sec.gov/Archives/edgar/data/1952244/000110465925105726/0001104659-25-105726-index.htm", "filing_date": "2025-11-03T18:15:25-05:00", "summary": "<b>Filed:</b> 2025-11-03 <b>AccNo:</b> 0001104659-25-105726 <b>Size:</b> 5 KB"}, {"title": "4 - ARES CAPITAL CORP (0001287750) (Issuer)", "filing_url": "https://www.sec.gov/Archives/edgar/data/1287750/000110465925105726/0001104659-25-105726-index.htm", "filing_date": "2025-11-03T18:15:25-05:00", "summary": "<b>Filed:</b> 2025-11-03 <b>AccNo:</b> 0001104659-25-105726 <b>Size:</b> 5 KB"}, {"title": "4 - Blakeway Amy E. (0002015075) (Reporting)", "filing_url": "https://www.sec.gov/Archives/edgar/data/2015075/000092805425000089/0000928054-25-000089-index.htm", "filing_date": "2025-11-03T18:06:34-05:00", "summary": "<b>Filed:</b> 2025-11-03 <b>AccNo:</b> 0000928054-25-000089 <b>Size:</b> 9 KB"}, {"title": "4 - FLOTEK INDUSTRIES INC/CN/ (0000928054) (Issuer)", "filing_url": "https://www.sec.gov/Archives/edgar/data/928054/000092805425000089/0000928054-25-000089-index.htm", "filing_date": "2025-11-03T18:06:34-05:00", "summary": "<b>Filed:</b> 2025-11-03 <b>AccNo:</b> 0000928054-25-000089 <b>Size:</b> 9 KB"}, {"title": "4 - Rowe Robert Scott (0001608962) (Reporting)", "filing_url": "https://www.sec.gov/Archives/edgar/data/1608962/000162828025048418/0001628280-25-048418-index.htm", "filing_date": "2025-11-03T18:06:31-05:00", "summary": "<b>Filed:</b> 2025-11-03 <b>AccNo:</b> 0001628280-25-048418 <b>Size:</b> 16 KB"}, {"title": "4 - FLOWSERVE CORP (0000030625) (Issuer)", "filing_url": "https://www.sec.gov/Archives/edgar/data/30625/000162828025048418/0001628280-25-048418-index.htm", "filing_date": "2025-11-03T18:06:31-05:00", "summary": "<b>Filed:</b> 2025-11-03 <b>AccNo:</b> 0001628280-25-048418 <b>Size:</b> 16 KB"}, {"title": "4 - Verisk Analytics, Inc. (0001442145) (Issuer)", "filing_url": "https://www.sec.gov/Archives/edgar/data/1442145/000119312525262910/0001193125-25-262910-index.htm", "filing_date": "2025-11-03T18:02:11-05:00", "summary": "<b>Filed:</b> 2025-11-03 <b>AccNo:</b> 0001193125-25-262910 <b>Size:</b> 4 KB"}, {"title": "4 - DAILEY JEFFREY J (0001278909) (Reporting)", "filing_url": "https://www.sec.gov/Archives/edgar/data/1278909/000119312525262910/0001193125-25-262910-index.htm", "filing_date": "2025-11-03T18:02:11-05:00", "summary": "<b>Filed:</b> 2025-11-03 <b>AccNo:</b> 0001193125-25-262910 <b>Size:</b> 4 KB"}, {"title": "4 - CLEMENT JAMES BOND (0001429215) (Reporting)", "filing_url": "https://www.sec.gov/Archives/edgar/data/1429215/000092805425000088/0000928054-25-000088-index.htm", "filing_date": "2025-11-03T18:01:53-05:00", "summary": "<b>Filed:</b> 2025-11-03 <b>AccNo:</b> 0000928054-25-000088 <b>Size:</b> 9 KB"}, {"title": "4 - FLOTEK INDUSTRIES INC/CN/ (0000928054) (Issuer)", "filing_url": "https://www.sec.gov/Archives/edgar/data/928054/000092805425000088/0000928054-25-000088-index.htm", "filing_date": "2025-11-03T18:01:53-05:00", "summary": "<b>Filed:</b> 2025-11-03 <b>AccNo:</b> 0000928054-25-000088 <b>Size:</b> 9 KB"}, {"title": "4 - WEIGAND DAVID E (0001777404) (Reporting)", "filing_url": "https://www.sec.gov/Archives/edgar/data/1777404/000177740425000014/0001777404-25-000014-index.htm", "filing_date": "2025-11-03T18:00:26-05:00", "summary": "<b>Filed:</b> 2025-11-03 <b>AccNo:</b> 0001777404-25-000014 <b>Size:</b> 8 KB"}, {"title": "4 - Super Micro Computer, Inc. (0001375365) (Issuer)", "filing_url": "https://www.sec.gov/Archives/edgar/data/1375365/000177740425000014/0001777404-25-000014-index.htm", "filing_date": "2025-11-03T18:00:26-05:00", "summary": "<b>Filed:</b> 2025-11-03 <b>AccNo:</b> 0001777404-25-000014 <b>Size:</b> 8 KB"}, {"title": "4 - Yap Kim Choy (0002081554) (Reporting)", "filing_url": "https://www.sec.gov/Archives/edgar/data/2081554/000149315225020647/0001493152-25-020647-index.htm", "filing_date": "2025-11-03T18:00:23-05:00", "summary": "<b>Filed:</b> 2025-11-03 <b>AccNo:</b> 0001493152-25-020647 <b>Size:</b> 4 KB"}, {"title": "4 - Bio Green Med Solution, Inc. (0001130166) (Issuer)", "filing_url": "https://www.sec.gov/Archives/edgar/data/1130166/000149315225020647/0001493152-25-020647-index.htm", "filing_date": "2025-11-03T18:00:23-05:00", "summary": "<b>Filed:</b> 2025-11-03 <b>AccNo:</b> 0001493152-25-020647 <b>Size:</b> 4 KB"}, {"title": "4 - Ezell Ryan Gillis (0001805598) (Reporting)", "filing_url": "https://www.sec.gov/Archives/edgar/data/1805598/000092805425000087/0000928054-25-000087-index.htm", "filing_date": "2025-11-03T18:00:14-05:00", "summary": "<b>Filed:</b> 2025-11-03 <b>AccNo:</b> 0000928054-25-000087 <b>Size:</b> 9 KB"}, {"title": "4 - FLOTEK INDUSTRIES INC/CN/ (0000928054) (Issuer)", "filing_url": "https://www.sec.gov/Archives/edgar/data/928054/000092805425000087/0000928054-25-000087-index.htm", "filing_date": "2025-11-03T18:00:14-05:00", "summary": "<b>Filed:</b> 2025-11-03 <b>AccNo:</b> 0000928054-25-000087 <b>Size:</b> 9 KB"}, {"title": "4 - Kua Khai Loon (0002081556) (Reporting)", "filing_url": "https://www.sec.gov/Archives/edgar/data/2081556/000149315225020645/0001493152-25-020645-index.htm", "filing_date": "2025-11-03T18:00:05-05:00", "summary": "<b>Filed:</b> 2025-11-03 <b>AccNo:</b> 0001493152-25-020645 <b>Size:</b> 4 KB"}, {"title": "4 - Bio Green Med Solution, Inc. (0001130166) (Issuer)", "filing_url": "https://www.sec.gov/Archives/edgar/data/1130166/000149315225020645/0001493152-25-020645-index.htm", "filing_date": "2025-11-03T18:00:05-05:00", "summary": "<b>Filed:</b> 2025-11-03 <b>AccNo:</b> 0001493152-25-020645 <b>Size:</b> 4 KB"}, {"title": "4 - Ong Yee Lung (0002081473) (Reporting)", "filing_url": "https://www.sec.gov/Archives/edgar/data/2081473/000149315225020644/0001493152-25-020644-index.htm", "filing_date": "2025-11-03T18:00:03-05:00", "summary": "<b>Filed:</b> 2025-11-03 <b>AccNo:</b> 0001493152-25-020644 <b>Size:</b> 4 KB"}, {"title": "4 - Bio Green Med Solution, Inc. (0001130166) (Issuer)", "filing_url": "https://www.sec.gov/Archives/edgar/data/1130166/000149315225020644/0001493152-25-020644-index.htm", "filing_date": "2025-11-03T18:00:03-05:00", "summary": "<b>Filed:</b> 2025-11-03 <b>AccNo:</b> 0001493152-25-020644 <b>Size:</b> 4 KB"}, {"title": "4 - Panayiotou Stacey J. (0001774162) (Reporting)", "filing_url": "https://www.sec.gov/Archives/edgar/data/1774162/000122520825008888/0001225208-25-008888-index.htm", "filing_date": "2025-11-03T17:59:50-05:00", "summary": "<b>Filed:</b> 2025-11-03 <b>AccNo:</b> 0001225208-25-008888 <b>Size:</b> 5 KB"}, {"title": "4 - KIMBERLY CLARK CORP (0000055785) (Issuer)", "filing_url": "https://www.sec.gov/Archives/edgar/data/55785/000122520825008888/0001225208-25-008888-index.htm", "filing_date": "2025-11-03T17:59:50-05:00", "summary": "<b>Filed:</b> 2025-11-03 <b>AccNo:</b> 0001225208-25-008888 <b>Size:</b> 5 KB"}, {"title": "4 - Wilson Kirk (0001654776) (Reporting)", "filing_url": "https://www.sec.gov/Archives/edgar/data/1654776/000162828025048410/0001628280-25-048410-index.htm", "filing_date": "2025-11-03T17:59:30-05:00", "summary": "<b>Filed:</b> 2025-11-03 <b>AccNo:</b> 0001628280-25-048410 <b>Size:</b> 18 KB"}, {"title": "4 - FLOWSERVE CORP (0000030625) (Issuer)", "filing_url": "https://www.sec.gov/Archives/edgar/data/30625/000162828025048410/0001628280-25-048410-index.htm", "filing_date": "2025-11-03T17:59:30-05:00", "summary": "<b>Filed:</b> 2025-11-03 <b>AccNo:</b> 0001628280-25-048410 <b>Size:</b> 18 KB"}, {"title": "4 - Carmichael John Patrick (0002087851) (Reporting)", "filing_url": "https://www.sec.gov/Archives/edgar/data/2087851/000122520825008887/0001225208-25-008887-index.htm", "filing_date": "2025-11-03T17:58:47-05:00", "summary": "<b>Filed:</b> 2025-11-03 <b>AccNo:</b> 0001225208-25-008887 <b>Size:</b> 5 KB"}, {"title": "4 - KIMBERLY CLARK CORP (0000055785) (Issuer)", "filing_url": "https://www.sec.gov/Archives/edgar/data/55785/000122520825008887/0001225208-25-008887-index.htm", "filing_date": "2025-11-03T17:58:47-05:00", "summary": "<b>Filed:</b> 2025-11-03 <b>AccNo:</b> 0001225208-25-008887 <b>Size:</b> 5 KB"}, {"title": "4 - Fenske Tamera (0001946526) (Reporting)", "filing_url": "https://www.sec.gov/Archives/edgar/data/1946526/000122520825008886/0001225208-25-008886-index.htm", "filing_date": "2025-11-03T17:58:45-05:00", "summary": "<b>Filed:</b> 2025-11-03 <b>AccNo:</b> 0001225208-25-008886 <b>Size:</b> 12 KB"}, {"title": "4 - KIMBERLY CLARK CORP (0000055785) (Issuer)", "filing_url": "https://www.sec.gov/Archives/edgar/data/55785/000122520825008886/0001225208-25-008886-index.htm", "filing_date": "2025-11-03T17:58:45-05:00", "summary": "<b>Filed:</b> 2025-11-03 <b>AccNo:</b> 0001225208-25-008886 <b>Size:</b> 12 KB"}, {"title": "4 - Purtill Sabra R. (0001876923) (Reporting)", "filing_url": "https://www.sec.gov/Archives/edgar/data/1876923/000119312525262897/0001193125-25-262897-index.htm", "filing_date": "2025-11-03T17:58:20-05:00", "summary": "<b>Filed:</b> 2025-11-03 <b>AccNo:</b> 0001193125-25-262897 <b>Size:</b> 4 KB"}, {"title": "4 - Verisk Analytics, Inc. (0001442145) (Issuer)", "filing_url": "https://www.sec.gov/Archives/edgar/data/1442145/000119312525262897/0001193125-25-262897-index.htm", "filing_date": "2025-11-03T17:58:20-05:00", "summary": "<b>Filed:</b> 2025-11-03 <b>AccNo:</b> 0001193125-25-262897 <b>Size:</b> 4 KB"}, {"title": "4 - Liu Liang Chiu-Chu Sara (0001392941) (Reporting)", "filing_url": "https://www.sec.gov/Archives/edgar/data/1392941/000139294125000014/0001392941-25-000014-index.htm", "filing_date": "2025-11-03T17:58:15-05:00", "summary": "<b>Filed:</b> 2025-11-03 <b>AccNo:</b> 0001392941-25-000014 <b>Size:</b> 10 KB"}, {"title": "4 - Super Micro Computer, Inc. (0001375365) (Issuer)", "filing_url": "https://www.sec.gov/Archives/edgar/data/1375365/000139294125000014/0001392941-25-000014-index.htm", "filing_date": "2025-11-03T17:58:15-05:00", "summary": "<b>Filed:</b> 2025-11-03 <b>AccNo:</b> 0001392941-25-000014 <b>Size:</b> 10 KB"}, {"title": "4 - CLEGG DON W (0001777241) (Reporting)", "filing_url": "https://www.sec.gov/Archives/edgar/data/1777241/000177724125000010/0001777241-25-000010-index.htm", "filing_date": "2025-11-03T17:56:37-05:00", "summary": "<b>Filed:</b> 2025-11-03 <b>AccNo:</b> 0001777241-25-000010 <b>Size:</b> 8 KB"}, {"title": "4 - Super Micro Computer, Inc. (0001375365) (Issuer)", "filing_url": "https://www.sec.gov/Archives/edgar/data/1375365/000177724125000010/0001777241-25-000010-index.htm", "filing_date": "2025-11-03T17:56:37-05:00", "summary": "<b>Filed:</b> 2025-11-03 <b>AccNo:</b> 0001777241-25-000010 <b>Size:</b> 8 KB"}, {"title": "4 - Hendrick Gregory (0001504870) (Reporting)", "filing_url": "https://www.sec.gov/Archives/edgar/data/1504870/000119312525262894/0001193125-25-262894-index.htm", "filing_date": "2025-11-03T17:56:16-05:00", "summary": "<b>Filed:</b> 2025-11-03 <b>AccNo:</b> 0001193125-25-262894 <b>Size:</b> 4 KB"}, {"title": "4 - Verisk Analytics, Inc. (0001442145) (Issuer)", "filing_url": "https://www.sec.gov/Archives/edgar/data/1442145/000119312525262894/0001193125-25-262894-index.htm", "filing_date": "2025-11-03T17:56:16-05:00", "summary": "<b>Filed:</b> 2025-11-03 <b>AccNo:</b> 0001193125-25-262894 <b>Size:</b> 4 KB"}, {"title": "4 - KAO GEORGE (0001777243) (Reporting)", "filing_url": "https://www.sec.gov/Archives/edgar/data/1777243/000177724325000012/0001777243-25-000012-index.htm", "filing_date": "2025-11-03T17:54:52-05:00", "summary": "<b>Filed:</b> 2025-11-03 <b>AccNo:</b> 0001777243-25-000012 <b>Size:</b> 8 KB"}, {"title": "4 - Super Micro Computer, Inc. (0001375365) (Issuer)", "filing_url": "https://www.sec.gov/Archives/edgar/data/1375365/000177724325000012/0001777243-25-000012-index.htm", "filing_date": "2025-11-03T17:54:52-05:00", "summary": "<b>Filed:</b> 2025-11-03 <b>AccNo:</b> 0001777243-25-000012 <b>Size:</b> 8 KB"}, {"title": "4 - Liaw Yih-Shyan Wally (0001392937) (Reporting)", "filing_url": "https://www.sec.gov/Archives/edgar/data/1392937/000139293725000010/0001392937-25-000010-index.htm", "filing_date": "2025-11-03T17:52:48-05:00", "summary": "<b>Filed:</b> 2025-11-03 <b>AccNo:</b> 0001392937-25-000010 <b>Size:</b> 10 KB"}, {"title": "4 - Super Micro Computer, Inc. (0001375365) (Issuer)", "filing_url": "https://www.sec.gov/Archives/edgar/data/1375365/000139293725000010/0001392937-25-000010-index.htm", "filing_date": "2025-11-03T17:52:48-05:00", "summary": "<b>Filed:</b> 2025-11-03 <b>AccNo:</b> 0001392937-25-000010 <b>Size:</b> 10 KB"}]