[{"title": "497K - NUVEEN INVESTMENT TRUST (0001013881) (Filer)", "filing_url": "https://www.sec.gov/Archives/edgar/data/1013881/000119312525259350/0001193125-25-259350-index.htm", "filing_date": "2025-10-31T06:17:21-04:00", "summary": "<b>Filed:</b> 2025-10-31 <b>AccNo:</b> 0001193125-25-259350 <b>Size:</b> 225 KB"}, {"title": "497K - NUVEEN INVESTMENT TRUST (0001013881) (Filer)", "filing_url": "https://www.sec.gov/Archives/edgar/data/1013881/000119312525259348/0001193125-25-259348-index.htm", "filing_date": "2025-10-31T06:15:58-04:00", "summary": "<b>Filed:</b> 2025-10-31 <b>AccNo:</b> 0001193125-25-259348 <b>Size:</b> 220 KB"}, {"title": "497K - NUVEEN INVESTMENT TRUST (0001013881) (Filer)", "filing_url": "https://www.sec.gov/Archives/edgar/data/1013881/000119312525259339/0001193125-25-259339-index.htm", "filing_date": "2025-10-31T06:14:41-04:00", "summary": "<b>Filed:</b> 2025-10-31 <b>AccNo:</b> 0001193125-25-259339 <b>Size:</b> 244 KB"}, {"title": "497K - NUVEEN INVESTMENT TRUST (0001013881) (Filer)", "filing_url": "https://www.sec.gov/Archives/edgar/data/1013881/000119312525259338/0001193125-25-259338-index.htm", "filing_date": "2025-10-31T06:13:31-04:00", "summary": "<b>Filed:</b> 2025-10-31 <b>AccNo:</b> 0001193125-25-259338 <b>Size:</b> 232 KB"}, {"title": "497K - NUVEEN INVESTMENT TRUST (0001013881) (Filer)", "filing_url": "https://www.sec.gov/Archives/edgar/data/1013881/000119312525259337/0001193125-25-259337-index.htm", "filing_date": "2025-10-31T06:12:15-04:00", "summary": "<b>Filed:</b> 2025-10-31 <b>AccNo:</b> 0001193125-25-259337 <b>Size:</b> 239 KB"}, {"title": "497J - NUVEEN INVESTMENT TRUST (0001013881) (Filer)", "filing_url": "https://www.sec.gov/Archives/edgar/data/1013881/000119312525259333/0001193125-25-259333-index.htm", "filing_date": "2025-10-31T06:11:07-04:00", "summary": "<b>Filed:</b> 2025-10-31 <b>AccNo:</b> 0001193125-25-259333 <b>Size:</b> 9 KB"}, {"title": "497K - NUVEEN INVESTMENT TRUST II (0001041673) (Filer)", "filing_url": "https://www.sec.gov/Archives/edgar/data/1041673/000119312525259329/0001193125-25-259329-index.htm", "filing_date": "2025-10-31T06:09:40-04:00", "summary": "<b>Filed:</b> 2025-10-31 <b>AccNo:</b> 0001193125-25-259329 <b>Size:</b> 205 KB"}, {"title": "497J - NUVEEN INVESTMENT TRUST II (0001041673) (Filer)", "filing_url": "https://www.sec.gov/Archives/edgar/data/1041673/000119312525259327/0001193125-25-259327-index.htm", "filing_date": "2025-10-31T06:08:34-04:00", "summary": "<b>Filed:</b> 2025-10-31 <b>AccNo:</b> 0001193125-25-259327 <b>Size:</b> 7 KB"}, {"title": "497K - NICHOLAS EQUITY INCOME FUND, INC. (0000913131) (Filer)", "filing_url": "https://www.sec.gov/Archives/edgar/data/913131/000119312525259326/0001193125-25-259326-index.htm", "filing_date": "2025-10-31T06:06:59-04:00", "summary": "<b>Filed:</b> 2025-10-31 <b>AccNo:</b> 0001193125-25-259326 <b>Size:</b> 7 KB"}, {"title": "497 - NICHOLAS EQUITY INCOME FUND, INC. (0000913131) (Filer)", "filing_url": "https://www.sec.gov/Archives/edgar/data/913131/000119312525259323/0001193125-25-259323-index.htm", "filing_date": "2025-10-31T06:05:49-04:00", "summary": "<b>Filed:</b> 2025-10-31 <b>AccNo:</b> 0001193125-25-259323 <b>Size:</b> 15 KB"}, {"title": "497K - NICHOLAS FUND, INC. (0000071958) (Filer)", "filing_url": "https://www.sec.gov/Archives/edgar/data/71958/000119312525259311/0001193125-25-259311-index.htm", "filing_date": "2025-10-31T06:04:42-04:00", "summary": "<b>Filed:</b> 2025-10-31 <b>AccNo:</b> 0001193125-25-259311 <b>Size:</b> 8 KB"}, {"title": "424B2 - CITIGROUP INC (0000831001) (Filer)", "filing_url": "https://www.sec.gov/Archives/edgar/data/831001/000191870425018665/0001918704-25-018665-index.htm", "filing_date": "2025-10-31T06:04:07-04:00", "summary": "<b>Filed:</b> 2025-10-31 <b>AccNo:</b> 0001918704-25-018665 <b>Size:</b> 407 KB"}, {"title": "424B2 - Citigroup Global Markets Holdings Inc. (0000200245) (Filer)", "filing_url": "https://www.sec.gov/Archives/edgar/data/200245/000191870425018665/0001918704-25-018665-index.htm", "filing_date": "2025-10-31T06:04:07-04:00", "summary": "<b>Filed:</b> 2025-10-31 <b>AccNo:</b> 0001918704-25-018665 <b>Size:</b> 407 KB"}, {"title": "497 - NICHOLAS FUND, INC. (0000071958) (Filer)", "filing_url": "https://www.sec.gov/Archives/edgar/data/71958/000119312525259307/0001193125-25-259307-index.htm", "filing_date": "2025-10-31T06:03:41-04:00", "summary": "<b>Filed:</b> 2025-10-31 <b>AccNo:</b> 0001193125-25-259307 <b>Size:</b> 13 KB"}, {"title": "424B2 - GS Finance Corp. (0001419828) (Filer)", "filing_url": "https://www.sec.gov/Archives/edgar/data/1419828/000119312525259131/0001193125-25-259131-index.htm", "filing_date": "2025-10-30T21:59:44-04:00", "summary": "<b>Filed:</b> 2025-10-31 <b>AccNo:</b> 0001193125-25-259131 <b>Size:</b> 455 KB"}, {"title": "424B2 - GOLDMAN SACHS GROUP INC (0000886982) (Filer)", "filing_url": "https://www.sec.gov/Archives/edgar/data/886982/000119312525259131/0001193125-25-259131-index.htm", "filing_date": "2025-10-30T21:59:44-04:00", "summary": "<b>Filed:</b> 2025-10-31 <b>AccNo:</b> 0001193125-25-259131 <b>Size:</b> 455 KB"}, {"title": "424B2 - CITIGROUP INC (0000831001) (Filer)", "filing_url": "https://www.sec.gov/Archives/edgar/data/831001/000095010325014038/0000950103-25-014038-index.htm", "filing_date": "2025-10-30T21:57:02-04:00", "summary": "<b>Filed:</b> 2025-10-31 <b>AccNo:</b> 0000950103-25-014038 <b>Size:</b> 86 KB"}, {"title": "424B2 - CITIGROUP INC (0000831001) (Filer)", "filing_url": "https://www.sec.gov/Archives/edgar/data/831001/000095010325014036/0000950103-25-014036-index.htm", "filing_date": "2025-10-30T21:56:59-04:00", "summary": "<b>Filed:</b> 2025-10-31 <b>AccNo:</b> 0000950103-25-014036 <b>Size:</b> 704 KB"}, {"title": "424B2 - Citigroup Global Markets Holdings Inc. (0000200245) (Filer)", "filing_url": "https://www.sec.gov/Archives/edgar/data/200245/000095010325014036/0000950103-25-014036-index.htm", "filing_date": "2025-10-30T21:56:59-04:00", "summary": "<b>Filed:</b> 2025-10-31 <b>AccNo:</b> 0000950103-25-014036 <b>Size:</b> 704 KB"}, {"title": "424B2 - CITIGROUP INC (0000831001) (Filer)", "filing_url": "https://www.sec.gov/Archives/edgar/data/831001/000095010325014033/0000950103-25-014033-index.htm", "filing_date": "2025-10-30T21:53:17-04:00", "summary": "<b>Filed:</b> 2025-10-31 <b>AccNo:</b> 0000950103-25-014033 <b>Size:</b> 89 KB"}, {"title": "424B2 - CITIGROUP INC (0000831001) (Filer)", "filing_url": "https://www.sec.gov/Archives/edgar/data/831001/000095010325014032/0000950103-25-014032-index.htm", "filing_date": "2025-10-30T21:49:20-04:00", "summary": "<b>Filed:</b> 2025-10-31 <b>AccNo:</b> 0000950103-25-014032 <b>Size:</b> 86 KB"}, {"title": "424B2 - CITIGROUP INC (0000831001) (Filer)", "filing_url": "https://www.sec.gov/Archives/edgar/data/831001/000095010325014030/0000950103-25-014030-index.htm", "filing_date": "2025-10-30T21:46:34-04:00", "summary": "<b>Filed:</b> 2025-10-31 <b>AccNo:</b> 0000950103-25-014030 <b>Size:</b> 86 KB"}, {"title": "424B2 - CITIGROUP INC (0000831001) (Filer)", "filing_url": "https://www.sec.gov/Archives/edgar/data/831001/000095010325014029/0000950103-25-014029-index.htm", "filing_date": "2025-10-30T21:40:07-04:00", "summary": "<b>Filed:</b> 2025-10-31 <b>AccNo:</b> 0000950103-25-014029 <b>Size:</b> 330 KB"}, {"title": "424B2 - Citigroup Global Markets Holdings Inc. (0000200245) (Filer)", "filing_url": "https://www.sec.gov/Archives/edgar/data/200245/000095010325014029/0000950103-25-014029-index.htm", "filing_date": "2025-10-30T21:40:07-04:00", "summary": "<b>Filed:</b> 2025-10-31 <b>AccNo:</b> 0000950103-25-014029 <b>Size:</b> 330 KB"}, {"title": "424B2 - CITIGROUP INC (0000831001) (Filer)", "filing_url": "https://www.sec.gov/Archives/edgar/data/831001/000095010325014028/0000950103-25-014028-index.htm", "filing_date": "2025-10-30T21:40:04-04:00", "summary": "<b>Filed:</b> 2025-10-31 <b>AccNo:</b> 0000950103-25-014028 <b>Size:</b> 86 KB"}, {"title": "4 - Schwab Charles R. (0000923738) (Reporting)", "filing_url": "https://www.sec.gov/Archives/edgar/data/923738/000092373825000037/0000923738-25-000037-index.htm", "filing_date": "2025-10-30T21:39:22-04:00", "summary": "<b>Filed:</b> 2025-10-30 <b>AccNo:</b> 0000923738-25-000037 <b>Size:</b> 9 KB"}, {"title": "4 - SCHWAB CHARLES CORP (0000316709) (Issuer)", "filing_url": "https://www.sec.gov/Archives/edgar/data/316709/000092373825000037/0000923738-25-000037-index.htm", "filing_date": "2025-10-30T21:39:22-04:00", "summary": "<b>Filed:</b> 2025-10-30 <b>AccNo:</b> 0000923738-25-000037 <b>Size:</b> 9 KB"}, {"title": "424B2 - CITIGROUP INC (0000831001) (Filer)", "filing_url": "https://www.sec.gov/Archives/edgar/data/831001/000095010325014027/0000950103-25-014027-index.htm", "filing_date": "2025-10-30T21:39:15-04:00", "summary": "<b>Filed:</b> 2025-10-31 <b>AccNo:</b> 0000950103-25-014027 <b>Size:</b> 84 KB"}, {"title": "425 - Steel Newco Inc. (0002082866) (Subject)", "filing_url": "https://www.sec.gov/Archives/edgar/data/2082866/000114036125039899/0001140361-25-039899-index.htm", "filing_date": "2025-10-30T21:38:45-04:00", "summary": "<b>Filed:</b> 2025-10-31 <b>AccNo:</b> 0001140361-25-039899 <b>Size:</b> 163 KB"}, {"title": "425 - SYNOVUS FINANCIAL CORP (0000018349) (Filed by)", "filing_url": "https://www.sec.gov/Archives/edgar/data/18349/000114036125039899/0001140361-25-039899-index.htm", "filing_date": "2025-10-30T21:38:45-04:00", "summary": "<b>Filed:</b> 2025-10-31 <b>AccNo:</b> 0001140361-25-039899 <b>Size:</b> 163 KB"}, {"title": "4 - ARTELO BIOSCIENCES, INC. (0001621221) (Issuer)", "filing_url": "https://www.sec.gov/Archives/edgar/data/1621221/000164033425001925/0001640334-25-001925-index.htm", "filing_date": "2025-10-30T21:30:05-04:00", "summary": "<b>Filed:</b> 2025-10-30 <b>AccNo:</b> 0001640334-25-001925 <b>Size:</b> 13 KB"}, {"title": "4 - MATSUI CONNIE (0001236537) (Reporting)", "filing_url": "https://www.sec.gov/Archives/edgar/data/1236537/000164033425001925/0001640334-25-001925-index.htm", "filing_date": "2025-10-30T21:30:05-04:00", "summary": "<b>Filed:</b> 2025-10-30 <b>AccNo:</b> 0001640334-25-001925 <b>Size:</b> 13 KB"}, {"title": "4 - ARTELO BIOSCIENCES, INC. (0001621221) (Issuer)", "filing_url": "https://www.sec.gov/Archives/edgar/data/1621221/000164033425001923/0001640334-25-001923-index.htm", "filing_date": "2025-10-30T21:28:31-04:00", "summary": "<b>Filed:</b> 2025-10-30 <b>AccNo:</b> 0001640334-25-001923 <b>Size:</b> 13 KB"}, {"title": "4 - FAVORITO TAMARA A (0001288232) (Reporting)", "filing_url": "https://www.sec.gov/Archives/edgar/data/1288232/000164033425001923/0001640334-25-001923-index.htm", "filing_date": "2025-10-30T21:28:31-04:00", "summary": "<b>Filed:</b> 2025-10-30 <b>AccNo:</b> 0001640334-25-001923 <b>Size:</b> 13 KB"}, {"title": "4 - ARTELO BIOSCIENCES, INC. (0001621221) (Issuer)", "filing_url": "https://www.sec.gov/Archives/edgar/data/1621221/000164033425001921/0001640334-25-001921-index.htm", "filing_date": "2025-10-30T21:27:37-04:00", "summary": "<b>Filed:</b> 2025-10-30 <b>AccNo:</b> 0001640334-25-001921 <b>Size:</b> 13 KB"}, {"title": "4 - Gorgas Gregory D. (0001526251) (Reporting)", "filing_url": "https://www.sec.gov/Archives/edgar/data/1526251/000164033425001921/0001640334-25-001921-index.htm", "filing_date": "2025-10-30T21:27:37-04:00", "summary": "<b>Filed:</b> 2025-10-30 <b>AccNo:</b> 0001640334-25-001921 <b>Size:</b> 13 KB"}, {"title": "424B2 - ROYAL BANK OF CANADA (0001000275) (Filer)", "filing_url": "https://www.sec.gov/Archives/edgar/data/1000275/000095010325014024/0000950103-25-014024-index.htm", "filing_date": "2025-10-30T21:22:01-04:00", "summary": "<b>Filed:</b> 2025-10-31 <b>AccNo:</b> 0000950103-25-014024 <b>Size:</b> 362 KB"}, {"title": "424B2 - JPMorgan Chase Financial Co. LLC (0001665650) (Filer)", "filing_url": "https://www.sec.gov/Archives/edgar/data/1665650/000121390025104354/0001213900-25-104354-index.htm", "filing_date": "2025-10-30T21:19:31-04:00", "summary": "<b>Filed:</b> 2025-10-31 <b>AccNo:</b> 0001213900-25-104354 <b>Size:</b> 3 MB"}, {"title": "424B2 - JPMORGAN CHASE & CO (0000019617) (Filer)", "filing_url": "https://www.sec.gov/Archives/edgar/data/19617/000121390025104354/0001213900-25-104354-index.htm", "filing_date": "2025-10-30T21:19:31-04:00", "summary": "<b>Filed:</b> 2025-10-31 <b>AccNo:</b> 0001213900-25-104354 <b>Size:</b> 3 MB"}, {"title": "424B2 - JPMorgan Chase Financial Co. LLC (0001665650) (Filer)", "filing_url": "https://www.sec.gov/Archives/edgar/data/1665650/000121390025104350/0001213900-25-104350-index.htm", "filing_date": "2025-10-30T21:15:03-04:00", "summary": "<b>Filed:</b> 2025-10-31 <b>AccNo:</b> 0001213900-25-104350 <b>Size:</b> 2 MB"}, {"title": "424B2 - JPMORGAN CHASE & CO (0000019617) (Filer)", "filing_url": "https://www.sec.gov/Archives/edgar/data/19617/000121390025104350/0001213900-25-104350-index.htm", "filing_date": "2025-10-30T21:15:03-04:00", "summary": "<b>Filed:</b> 2025-10-31 <b>AccNo:</b> 0001213900-25-104350 <b>Size:</b> 2 MB"}, {"title": "424B2 - JPMorgan Chase Financial Co. LLC (0001665650) (Filer)", "filing_url": "https://www.sec.gov/Archives/edgar/data/1665650/000121390025104348/0001213900-25-104348-index.htm", "filing_date": "2025-10-30T21:13:17-04:00", "summary": "<b>Filed:</b> 2025-10-31 <b>AccNo:</b> 0001213900-25-104348 <b>Size:</b> 2 MB"}, {"title": "424B2 - JPMORGAN CHASE & CO (0000019617) (Filer)", "filing_url": "https://www.sec.gov/Archives/edgar/data/19617/000121390025104348/0001213900-25-104348-index.htm", "filing_date": "2025-10-30T21:13:17-04:00", "summary": "<b>Filed:</b> 2025-10-31 <b>AccNo:</b> 0001213900-25-104348 <b>Size:</b> 2 MB"}, {"title": "4 - ICEBERY LTD (0002004292) (Reporting)", "filing_url": "https://www.sec.gov/Archives/edgar/data/2004292/000200414125000008/0002004141-25-000008-index.htm", "filing_date": "2025-10-30T21:11:58-04:00", "summary": "<b>Filed:</b> 2025-10-30 <b>AccNo:</b> 0002004141-25-000008 <b>Size:</b> 7 KB"}, {"title": "4 - Hao Xinyan (0002004141) (Reporting)", "filing_url": "https://www.sec.gov/Archives/edgar/data/2004141/000200414125000008/0002004141-25-000008-index.htm", "filing_date": "2025-10-30T21:11:58-04:00", "summary": "<b>Filed:</b> 2025-10-30 <b>AccNo:</b> 0002004141-25-000008 <b>Size:</b> 7 KB"}, {"title": "4 - GigaCloud Technology Inc (0001857816) (Issuer)", "filing_url": "https://www.sec.gov/Archives/edgar/data/1857816/000200414125000008/0002004141-25-000008-index.htm", "filing_date": "2025-10-30T21:11:58-04:00", "summary": "<b>Filed:</b> 2025-10-30 <b>AccNo:</b> 0002004141-25-000008 <b>Size:</b> 7 KB"}, {"title": "424B2 - JPMorgan Chase Financial Co. LLC (0001665650) (Filer)", "filing_url": "https://www.sec.gov/Archives/edgar/data/1665650/000121390025104347/0001213900-25-104347-index.htm", "filing_date": "2025-10-30T21:10:47-04:00", "summary": "<b>Filed:</b> 2025-10-31 <b>AccNo:</b> 0001213900-25-104347 <b>Size:</b> 2 MB"}, {"title": "424B2 - JPMORGAN CHASE & CO (0000019617) (Filer)", "filing_url": "https://www.sec.gov/Archives/edgar/data/19617/000121390025104347/0001213900-25-104347-index.htm", "filing_date": "2025-10-30T21:10:47-04:00", "summary": "<b>Filed:</b> 2025-10-31 <b>AccNo:</b> 0001213900-25-104347 <b>Size:</b> 2 MB"}, {"title": "424B2 - JPMorgan Chase Financial Co. LLC (0001665650) (Filer)", "filing_url": "https://www.sec.gov/Archives/edgar/data/1665650/000121390025104343/0001213900-25-104343-index.htm", "filing_date": "2025-10-30T20:58:52-04:00", "summary": "<b>Filed:</b> 2025-10-31 <b>AccNo:</b> 0001213900-25-104343 <b>Size:</b> 140 KB"}, {"title": "424B2 - JPMORGAN CHASE & CO (0000019617) (Filer)", "filing_url": "https://www.sec.gov/Archives/edgar/data/19617/000121390025104343/0001213900-25-104343-index.htm", "filing_date": "2025-10-30T20:58:52-04:00", "summary": "<b>Filed:</b> 2025-10-31 <b>AccNo:</b> 0001213900-25-104343 <b>Size:</b> 140 KB"}]