[{"title": "424B2 - GS Finance Corp. (0001419828) (Filer)", "filing_url": "https://www.sec.gov/Archives/edgar/data/1419828/000119312525246537/0001193125-25-246537-index.htm", "filing_date": "2025-10-22T14:49:10-04:00", "summary": "<b>Filed:</b> 2025-10-22 <b>AccNo:</b> 0001193125-25-246537 <b>Size:</b> 385 KB"}, {"title": "424B2 - GOLDMAN SACHS GROUP INC (0000886982) (Filer)", "filing_url": "https://www.sec.gov/Archives/edgar/data/886982/000119312525246537/0001193125-25-246537-index.htm", "filing_date": "2025-10-22T14:49:10-04:00", "summary": "<b>Filed:</b> 2025-10-22 <b>AccNo:</b> 0001193125-25-246537 <b>Size:</b> 385 KB"}, {"title": "485BPOS - JPMorgan Trust I (0001217286) (Filer)", "filing_url": "https://www.sec.gov/Archives/edgar/data/1217286/000119312525246532/0001193125-25-246532-index.htm", "filing_date": "2025-10-22T14:48:31-04:00", "summary": "<b>Filed:</b> 2025-10-22 <b>AccNo:</b> 0001193125-25-246532 <b>Size:</b> 70 MB"}, {"title": "485BPOS - JPMorgan Trust I (0001217286) (Filer)", "filing_url": "https://www.sec.gov/Archives/edgar/data/1217286/000119312525246532/0001193125-25-246532-index.htm", "filing_date": "2025-10-22T14:48:31-04:00", "summary": "<b>Filed:</b> 2025-10-22 <b>AccNo:</b> 0001193125-25-246532 <b>Size:</b> 70 MB"}, {"title": "424B2 - JPMorgan Chase Financial Co. LLC (0001665650) (Filer)", "filing_url": "https://www.sec.gov/Archives/edgar/data/1665650/000121390025101148/0001213900-25-101148-index.htm", "filing_date": "2025-10-22T14:48:03-04:00", "summary": "<b>Filed:</b> 2025-10-22 <b>AccNo:</b> 0001213900-25-101148 <b>Size:</b> 420 KB"}, {"title": "424B2 - JPMORGAN CHASE & CO (0000019617) (Filer)", "filing_url": "https://www.sec.gov/Archives/edgar/data/19617/000121390025101148/0001213900-25-101148-index.htm", "filing_date": "2025-10-22T14:48:03-04:00", "summary": "<b>Filed:</b> 2025-10-22 <b>AccNo:</b> 0001213900-25-101148 <b>Size:</b> 420 KB"}, {"title": "424B3 - IPC Alternative Real Estate Income Trust, Inc. (0001959961) (Filer)", "filing_url": "https://www.sec.gov/Archives/edgar/data/1959961/000119312525246530/0001193125-25-246530-index.htm", "filing_date": "2025-10-22T14:46:01-04:00", "summary": "<b>Filed:</b> 2025-10-22 <b>AccNo:</b> 0001193125-25-246530 <b>Size:</b> 10 KB"}, {"title": "424B2 - JPMorgan Chase Financial Co. LLC (0001665650) (Filer)", "filing_url": "https://www.sec.gov/Archives/edgar/data/1665650/000121390025101147/0001213900-25-101147-index.htm", "filing_date": "2025-10-22T14:45:30-04:00", "summary": "<b>Filed:</b> 2025-10-22 <b>AccNo:</b> 0001213900-25-101147 <b>Size:</b> 2 MB"}, {"title": "424B2 - JPMORGAN CHASE & CO (0000019617) (Filer)", "filing_url": "https://www.sec.gov/Archives/edgar/data/19617/000121390025101147/0001213900-25-101147-index.htm", "filing_date": "2025-10-22T14:45:30-04:00", "summary": "<b>Filed:</b> 2025-10-22 <b>AccNo:</b> 0001213900-25-101147 <b>Size:</b> 2 MB"}, {"title": "497 - GOLDMAN SACHS TRUST (0000822977) (Filer)", "filing_url": "https://www.sec.gov/Archives/edgar/data/822977/000119312525246525/0001193125-25-246525-index.htm", "filing_date": "2025-10-22T14:43:47-04:00", "summary": "<b>Filed:</b> 2025-10-22 <b>AccNo:</b> 0001193125-25-246525 <b>Size:</b> 7 KB"}, {"title": "424B2 - GS Finance Corp. (0001419828) (Filer)", "filing_url": "https://www.sec.gov/Archives/edgar/data/1419828/000119312525246524/0001193125-25-246524-index.htm", "filing_date": "2025-10-22T14:43:41-04:00", "summary": "<b>Filed:</b> 2025-10-22 <b>AccNo:</b> 0001193125-25-246524 <b>Size:</b> 453 KB"}, {"title": "424B2 - GOLDMAN SACHS GROUP INC (0000886982) (Filer)", "filing_url": "https://www.sec.gov/Archives/edgar/data/886982/000119312525246524/0001193125-25-246524-index.htm", "filing_date": "2025-10-22T14:43:41-04:00", "summary": "<b>Filed:</b> 2025-10-22 <b>AccNo:</b> 0001193125-25-246524 <b>Size:</b> 453 KB"}, {"title": "424B2 - JPMorgan Chase Financial Co. LLC (0001665650) (Filer)", "filing_url": "https://www.sec.gov/Archives/edgar/data/1665650/000121390025101144/0001213900-25-101144-index.htm", "filing_date": "2025-10-22T14:42:55-04:00", "summary": "<b>Filed:</b> 2025-10-22 <b>AccNo:</b> 0001213900-25-101144 <b>Size:</b> 3 MB"}, {"title": "424B2 - JPMORGAN CHASE & CO (0000019617) (Filer)", "filing_url": "https://www.sec.gov/Archives/edgar/data/19617/000121390025101144/0001213900-25-101144-index.htm", "filing_date": "2025-10-22T14:42:55-04:00", "summary": "<b>Filed:</b> 2025-10-22 <b>AccNo:</b> 0001213900-25-101144 <b>Size:</b> 3 MB"}, {"title": "424B2 - CITIGROUP INC (0000831001) (Filer)", "filing_url": "https://www.sec.gov/Archives/edgar/data/831001/000095010325013509/0000950103-25-013509-index.htm", "filing_date": "2025-10-22T14:41:37-04:00", "summary": "<b>Filed:</b> 2025-10-22 <b>AccNo:</b> 0000950103-25-013509 <b>Size:</b> 147 KB"}, {"title": "424B2 - Citigroup Global Markets Holdings Inc. (0000200245) (Filer)", "filing_url": "https://www.sec.gov/Archives/edgar/data/200245/000095010325013509/0000950103-25-013509-index.htm", "filing_date": "2025-10-22T14:41:37-04:00", "summary": "<b>Filed:</b> 2025-10-22 <b>AccNo:</b> 0000950103-25-013509 <b>Size:</b> 147 KB"}, {"title": "424B2 - CITIGROUP INC (0000831001) (Filer)", "filing_url": "https://www.sec.gov/Archives/edgar/data/831001/000191870425017942/0001918704-25-017942-index.htm", "filing_date": "2025-10-22T14:41:14-04:00", "summary": "<b>Filed:</b> 2025-10-22 <b>AccNo:</b> 0001918704-25-017942 <b>Size:</b> 1 MB"}, {"title": "424B2 - Citigroup Global Markets Holdings Inc. (0000200245) (Filer)", "filing_url": "https://www.sec.gov/Archives/edgar/data/200245/000191870425017942/0001918704-25-017942-index.htm", "filing_date": "2025-10-22T14:41:14-04:00", "summary": "<b>Filed:</b> 2025-10-22 <b>AccNo:</b> 0001918704-25-017942 <b>Size:</b> 1 MB"}, {"title": "424B2 - JPMorgan Chase Financial Co. LLC (0001665650) (Filer)", "filing_url": "https://www.sec.gov/Archives/edgar/data/1665650/000121390025101143/0001213900-25-101143-index.htm", "filing_date": "2025-10-22T14:40:40-04:00", "summary": "<b>Filed:</b> 2025-10-22 <b>AccNo:</b> 0001213900-25-101143 <b>Size:</b> 2 MB"}, {"title": "424B2 - JPMORGAN CHASE & CO (0000019617) (Filer)", "filing_url": "https://www.sec.gov/Archives/edgar/data/19617/000121390025101143/0001213900-25-101143-index.htm", "filing_date": "2025-10-22T14:40:40-04:00", "summary": "<b>Filed:</b> 2025-10-22 <b>AccNo:</b> 0001213900-25-101143 <b>Size:</b> 2 MB"}, {"title": "424B2 - CITIGROUP INC (0000831001) (Filer)", "filing_url": "https://www.sec.gov/Archives/edgar/data/831001/000095010325013508/0000950103-25-013508-index.htm", "filing_date": "2025-10-22T14:40:15-04:00", "summary": "<b>Filed:</b> 2025-10-22 <b>AccNo:</b> 0000950103-25-013508 <b>Size:</b> 138 KB"}, {"title": "424B2 - Citigroup Global Markets Holdings Inc. (0000200245) (Filer)", "filing_url": "https://www.sec.gov/Archives/edgar/data/200245/000095010325013508/0000950103-25-013508-index.htm", "filing_date": "2025-10-22T14:40:15-04:00", "summary": "<b>Filed:</b> 2025-10-22 <b>AccNo:</b> 0000950103-25-013508 <b>Size:</b> 138 KB"}, {"title": "424B2 - CITIGROUP INC (0000831001) (Filer)", "filing_url": "https://www.sec.gov/Archives/edgar/data/831001/000191870425017941/0001918704-25-017941-index.htm", "filing_date": "2025-10-22T14:37:35-04:00", "summary": "<b>Filed:</b> 2025-10-22 <b>AccNo:</b> 0001918704-25-017941 <b>Size:</b> 973 KB"}, {"title": "424B2 - Citigroup Global Markets Holdings Inc. (0000200245) (Filer)", "filing_url": "https://www.sec.gov/Archives/edgar/data/200245/000191870425017941/0001918704-25-017941-index.htm", "filing_date": "2025-10-22T14:37:35-04:00", "summary": "<b>Filed:</b> 2025-10-22 <b>AccNo:</b> 0001918704-25-017941 <b>Size:</b> 973 KB"}, {"title": "4 - HARTZ CHARLES SCOTT (0001230669) (Reporting)", "filing_url": "https://www.sec.gov/Archives/edgar/data/1230669/000162828025045835/0001628280-25-045835-index.htm", "filing_date": "2025-10-22T14:37:30-04:00", "summary": "<b>Filed:</b> 2025-10-22 <b>AccNo:</b> 0001628280-25-045835 <b>Size:</b> 6 KB"}, {"title": "4 - ERIE INDEMNITY CO (0000922621) (Issuer)", "filing_url": "https://www.sec.gov/Archives/edgar/data/922621/000162828025045835/0001628280-25-045835-index.htm", "filing_date": "2025-10-22T14:37:30-04:00", "summary": "<b>Filed:</b> 2025-10-22 <b>AccNo:</b> 0001628280-25-045835 <b>Size:</b> 6 KB"}, {"title": "424B2 - CITIGROUP INC (0000831001) (Filer)", "filing_url": "https://www.sec.gov/Archives/edgar/data/831001/000095010325013507/0000950103-25-013507-index.htm", "filing_date": "2025-10-22T14:37:18-04:00", "summary": "<b>Filed:</b> 2025-10-22 <b>AccNo:</b> 0000950103-25-013507 <b>Size:</b> 692 KB"}, {"title": "424B2 - Citigroup Global Markets Holdings Inc. (0000200245) (Filer)", "filing_url": "https://www.sec.gov/Archives/edgar/data/200245/000095010325013507/0000950103-25-013507-index.htm", "filing_date": "2025-10-22T14:37:18-04:00", "summary": "<b>Filed:</b> 2025-10-22 <b>AccNo:</b> 0000950103-25-013507 <b>Size:</b> 692 KB"}, {"title": "424B2 - GS Finance Corp. (0001419828) (Filer)", "filing_url": "https://www.sec.gov/Archives/edgar/data/1419828/000119312525246518/0001193125-25-246518-index.htm", "filing_date": "2025-10-22T14:35:58-04:00", "summary": "<b>Filed:</b> 2025-10-22 <b>AccNo:</b> 0001193125-25-246518 <b>Size:</b> 911 KB"}, {"title": "424B2 - GOLDMAN SACHS GROUP INC (0000886982) (Filer)", "filing_url": "https://www.sec.gov/Archives/edgar/data/886982/000119312525246518/0001193125-25-246518-index.htm", "filing_date": "2025-10-22T14:35:58-04:00", "summary": "<b>Filed:</b> 2025-10-22 <b>AccNo:</b> 0001193125-25-246518 <b>Size:</b> 911 KB"}, {"title": "424B2 - CITIGROUP INC (0000831001) (Filer)", "filing_url": "https://www.sec.gov/Archives/edgar/data/831001/000095010325013506/0000950103-25-013506-index.htm", "filing_date": "2025-10-22T14:32:40-04:00", "summary": "<b>Filed:</b> 2025-10-22 <b>AccNo:</b> 0000950103-25-013506 <b>Size:</b> 363 KB"}, {"title": "424B2 - Citigroup Global Markets Holdings Inc. (0000200245) (Filer)", "filing_url": "https://www.sec.gov/Archives/edgar/data/200245/000095010325013506/0000950103-25-013506-index.htm", "filing_date": "2025-10-22T14:32:40-04:00", "summary": "<b>Filed:</b> 2025-10-22 <b>AccNo:</b> 0000950103-25-013506 <b>Size:</b> 363 KB"}, {"title": "485BXT - WisdomTree Digital Trust (0001859001) (Filer)", "filing_url": "https://www.sec.gov/Archives/edgar/data/1859001/000121465925015189/0001214659-25-015189-index.htm", "filing_date": "2025-10-22T14:30:34-04:00", "summary": "<b>Filed:</b> 2025-10-22 <b>AccNo:</b> 0001214659-25-015189 <b>Size:</b> 18 KB"}, {"title": "485BXT - WisdomTree Digital Trust (0001859001) (Filer)", "filing_url": "https://www.sec.gov/Archives/edgar/data/1859001/000121465925015189/0001214659-25-015189-index.htm", "filing_date": "2025-10-22T14:30:34-04:00", "summary": "<b>Filed:</b> 2025-10-22 <b>AccNo:</b> 0001214659-25-015189 <b>Size:</b> 18 KB"}, {"title": "4 - Hagen Thomas B (0001396809) (Reporting)", "filing_url": "https://www.sec.gov/Archives/edgar/data/1396809/000162828025045833/0001628280-25-045833-index.htm", "filing_date": "2025-10-22T14:26:34-04:00", "summary": "<b>Filed:</b> 2025-10-22 <b>AccNo:</b> 0001628280-25-045833 <b>Size:</b> 14 KB"}, {"title": "4 - ERIE INDEMNITY CO (0000922621) (Issuer)", "filing_url": "https://www.sec.gov/Archives/edgar/data/922621/000162828025045833/0001628280-25-045833-index.htm", "filing_date": "2025-10-22T14:26:34-04:00", "summary": "<b>Filed:</b> 2025-10-22 <b>AccNo:</b> 0001628280-25-045833 <b>Size:</b> 14 KB"}, {"title": "424B2 - CITIGROUP INC (0000831001) (Filer)", "filing_url": "https://www.sec.gov/Archives/edgar/data/831001/000191870425017940/0001918704-25-017940-index.htm", "filing_date": "2025-10-22T14:25:43-04:00", "summary": "<b>Filed:</b> 2025-10-22 <b>AccNo:</b> 0001918704-25-017940 <b>Size:</b> 1 MB"}, {"title": "424B2 - Citigroup Global Markets Holdings Inc. (0000200245) (Filer)", "filing_url": "https://www.sec.gov/Archives/edgar/data/200245/000191870425017940/0001918704-25-017940-index.htm", "filing_date": "2025-10-22T14:25:43-04:00", "summary": "<b>Filed:</b> 2025-10-22 <b>AccNo:</b> 0001918704-25-017940 <b>Size:</b> 1 MB"}, {"title": "424B2 - CITIGROUP INC (0000831001) (Filer)", "filing_url": "https://www.sec.gov/Archives/edgar/data/831001/000191870425017939/0001918704-25-017939-index.htm", "filing_date": "2025-10-22T14:21:56-04:00", "summary": "<b>Filed:</b> 2025-10-22 <b>AccNo:</b> 0001918704-25-017939 <b>Size:</b> 815 KB"}, {"title": "424B2 - Citigroup Global Markets Holdings Inc. (0000200245) (Filer)", "filing_url": "https://www.sec.gov/Archives/edgar/data/200245/000191870425017939/0001918704-25-017939-index.htm", "filing_date": "2025-10-22T14:21:56-04:00", "summary": "<b>Filed:</b> 2025-10-22 <b>AccNo:</b> 0001918704-25-017939 <b>Size:</b> 815 KB"}, {"title": "424B2 - CITIGROUP INC (0000831001) (Filer)", "filing_url": "https://www.sec.gov/Archives/edgar/data/831001/000095010325013505/0000950103-25-013505-index.htm", "filing_date": "2025-10-22T14:21:52-04:00", "summary": "<b>Filed:</b> 2025-10-22 <b>AccNo:</b> 0000950103-25-013505 <b>Size:</b> 584 KB"}, {"title": "424B2 - Citigroup Global Markets Holdings Inc. (0000200245) (Filer)", "filing_url": "https://www.sec.gov/Archives/edgar/data/200245/000095010325013505/0000950103-25-013505-index.htm", "filing_date": "2025-10-22T14:21:52-04:00", "summary": "<b>Filed:</b> 2025-10-22 <b>AccNo:</b> 0000950103-25-013505 <b>Size:</b> 584 KB"}, {"title": "424B2 - CITIGROUP INC (0000831001) (Filer)", "filing_url": "https://www.sec.gov/Archives/edgar/data/831001/000191870425017938/0001918704-25-017938-index.htm", "filing_date": "2025-10-22T14:21:23-04:00", "summary": "<b>Filed:</b> 2025-10-22 <b>AccNo:</b> 0001918704-25-017938 <b>Size:</b> 1 MB"}, {"title": "424B2 - Citigroup Global Markets Holdings Inc. (0000200245) (Filer)", "filing_url": "https://www.sec.gov/Archives/edgar/data/200245/000191870425017938/0001918704-25-017938-index.htm", "filing_date": "2025-10-22T14:21:23-04:00", "summary": "<b>Filed:</b> 2025-10-22 <b>AccNo:</b> 0001918704-25-017938 <b>Size:</b> 1 MB"}, {"title": "424B2 - BofA Finance LLC (0001682472) (Filer)", "filing_url": "https://www.sec.gov/Archives/edgar/data/1682472/000191870425017937/0001918704-25-017937-index.htm", "filing_date": "2025-10-22T14:20:54-04:00", "summary": "<b>Filed:</b> 2025-10-22 <b>AccNo:</b> 0001918704-25-017937 <b>Size:</b> 698 KB"}, {"title": "424B2 - BANK OF AMERICA CORP /DE/ (0000070858) (Filer)", "filing_url": "https://www.sec.gov/Archives/edgar/data/70858/000191870425017937/0001918704-25-017937-index.htm", "filing_date": "2025-10-22T14:20:54-04:00", "summary": "<b>Filed:</b> 2025-10-22 <b>AccNo:</b> 0001918704-25-017937 <b>Size:</b> 698 KB"}, {"title": "4 - Henriksen Michael Gregory Max (0001994096) (Reporting)", "filing_url": "https://www.sec.gov/Archives/edgar/data/1994096/000149315225018891/0001493152-25-018891-index.htm", "filing_date": "2025-10-22T14:19:28-04:00", "summary": "<b>Filed:</b> 2025-10-22 <b>AccNo:</b> 0001493152-25-018891 <b>Size:</b> 4 KB"}, {"title": "4 - Livento Group, Inc. (0001593549) (Issuer)", "filing_url": "https://www.sec.gov/Archives/edgar/data/1593549/000149315225018891/0001493152-25-018891-index.htm", "filing_date": "2025-10-22T14:19:28-04:00", "summary": "<b>Filed:</b> 2025-10-22 <b>AccNo:</b> 0001493152-25-018891 <b>Size:</b> 4 KB"}, {"title": "424B2 - BANK OF NOVA SCOTIA (0000009631) (Filer)", "filing_url": "https://www.sec.gov/Archives/edgar/data/9631/000183988225059917/0001839882-25-059917-index.htm", "filing_date": "2025-10-22T14:19:24-04:00", "summary": "<b>Filed:</b> 2025-10-22 <b>AccNo:</b> 0001839882-25-059917 <b>Size:</b> 844 KB"}, {"title": "424B2 - CITIGROUP INC (0000831001) (Filer)", "filing_url": "https://www.sec.gov/Archives/edgar/data/831001/000191870425017936/0001918704-25-017936-index.htm", "filing_date": "2025-10-22T14:19:06-04:00", "summary": "<b>Filed:</b> 2025-10-22 <b>AccNo:</b> 0001918704-25-017936 <b>Size:</b> 634 KB"}]