[{"title": "4 - Myrmikan Capital, LLC (0001965935) (Reporting)", "filing_url": "https://www.sec.gov/Archives/edgar/data/1965935/000206483525000023/0002064835-25-000023-index.htm", "filing_date": "2025-10-28T21:55:44-04:00", "summary": "<b>Filed:</b> 2025-10-28 <b>AccNo:</b> 0002064835-25-000023 <b>Size:</b> 29 KB"}, {"title": "4 - Oliver Daniel Jr (0001965660) (Reporting)", "filing_url": "https://www.sec.gov/Archives/edgar/data/1965660/000206483525000023/0002064835-25-000023-index.htm", "filing_date": "2025-10-28T21:55:44-04:00", "summary": "<b>Filed:</b> 2025-10-28 <b>AccNo:</b> 0002064835-25-000023 <b>Size:</b> 29 KB"}, {"title": "4 - Myrmikan Gold Fund, LLC (0001848738) (Reporting)", "filing_url": "https://www.sec.gov/Archives/edgar/data/1848738/000206483525000023/0002064835-25-000023-index.htm", "filing_date": "2025-10-28T21:55:44-04:00", "summary": "<b>Filed:</b> 2025-10-28 <b>AccNo:</b> 0002064835-25-000023 <b>Size:</b> 29 KB"}, {"title": "4 - Rise Gold Corp. (0001424864) (Issuer)", "filing_url": "https://www.sec.gov/Archives/edgar/data/1424864/000206483525000023/0002064835-25-000023-index.htm", "filing_date": "2025-10-28T21:55:44-04:00", "summary": "<b>Filed:</b> 2025-10-28 <b>AccNo:</b> 0002064835-25-000023 <b>Size:</b> 29 KB"}, {"title": "4 - Tseng Saria (0001312593) (Reporting)", "filing_url": "https://www.sec.gov/Archives/edgar/data/1312593/000121465925015478/0001214659-25-015478-index.htm", "filing_date": "2025-10-28T21:38:53-04:00", "summary": "<b>Filed:</b> 2025-10-28 <b>AccNo:</b> 0001214659-25-015478 <b>Size:</b> 5 KB"}, {"title": "4 - MONOLITHIC POWER SYSTEMS INC (0001280452) (Issuer)", "filing_url": "https://www.sec.gov/Archives/edgar/data/1280452/000121465925015478/0001214659-25-015478-index.htm", "filing_date": "2025-10-28T21:38:53-04:00", "summary": "<b>Filed:</b> 2025-10-28 <b>AccNo:</b> 0001214659-25-015478 <b>Size:</b> 5 KB"}, {"title": "4 - BLEGEN THEODORE (0001415033) (Reporting)", "filing_url": "https://www.sec.gov/Archives/edgar/data/1415033/000121465925015477/0001214659-25-015477-index.htm", "filing_date": "2025-10-28T21:38:17-04:00", "summary": "<b>Filed:</b> 2025-10-28 <b>AccNo:</b> 0001214659-25-015477 <b>Size:</b> 6 KB"}, {"title": "4 - MONOLITHIC POWER SYSTEMS INC (0001280452) (Issuer)", "filing_url": "https://www.sec.gov/Archives/edgar/data/1280452/000121465925015477/0001214659-25-015477-index.htm", "filing_date": "2025-10-28T21:38:17-04:00", "summary": "<b>Filed:</b> 2025-10-28 <b>AccNo:</b> 0001214659-25-015477 <b>Size:</b> 6 KB"}, {"title": "4 - Hsing Michael (0001308676) (Reporting)", "filing_url": "https://www.sec.gov/Archives/edgar/data/1308676/000121465925015476/0001214659-25-015476-index.htm", "filing_date": "2025-10-28T21:37:20-04:00", "summary": "<b>Filed:</b> 2025-10-28 <b>AccNo:</b> 0001214659-25-015476 <b>Size:</b> 6 KB"}, {"title": "4 - MONOLITHIC POWER SYSTEMS INC (0001280452) (Issuer)", "filing_url": "https://www.sec.gov/Archives/edgar/data/1280452/000121465925015476/0001214659-25-015476-index.htm", "filing_date": "2025-10-28T21:37:20-04:00", "summary": "<b>Filed:</b> 2025-10-28 <b>AccNo:</b> 0001214659-25-015476 <b>Size:</b> 6 KB"}, {"title": "4 - Xiao Deming (0001308647) (Reporting)", "filing_url": "https://www.sec.gov/Archives/edgar/data/1308647/000121465925015475/0001214659-25-015475-index.htm", "filing_date": "2025-10-28T21:36:16-04:00", "summary": "<b>Filed:</b> 2025-10-28 <b>AccNo:</b> 0001214659-25-015475 <b>Size:</b> 6 KB"}, {"title": "4 - MONOLITHIC POWER SYSTEMS INC (0001280452) (Issuer)", "filing_url": "https://www.sec.gov/Archives/edgar/data/1280452/000121465925015475/0001214659-25-015475-index.htm", "filing_date": "2025-10-28T21:36:16-04:00", "summary": "<b>Filed:</b> 2025-10-28 <b>AccNo:</b> 0001214659-25-015475 <b>Size:</b> 6 KB"}, {"title": "4 - Sciammas Maurice (0001360833) (Reporting)", "filing_url": "https://www.sec.gov/Archives/edgar/data/1360833/000121465925015474/0001214659-25-015474-index.htm", "filing_date": "2025-10-28T21:35:34-04:00", "summary": "<b>Filed:</b> 2025-10-28 <b>AccNo:</b> 0001214659-25-015474 <b>Size:</b> 14 KB"}, {"title": "4 - MONOLITHIC POWER SYSTEMS INC (0001280452) (Issuer)", "filing_url": "https://www.sec.gov/Archives/edgar/data/1280452/000121465925015474/0001214659-25-015474-index.htm", "filing_date": "2025-10-28T21:35:34-04:00", "summary": "<b>Filed:</b> 2025-10-28 <b>AccNo:</b> 0001214659-25-015474 <b>Size:</b> 14 KB"}, {"title": "4 - PennyMac Financial Services, Inc. (0001745916) (Issuer)", "filing_url": "https://www.sec.gov/Archives/edgar/data/1745916/000174591625000021/0001745916-25-000021-index.htm", "filing_date": "2025-10-28T21:34:57-04:00", "summary": "<b>Filed:</b> 2025-10-28 <b>AccNo:</b> 0001745916-25-000021 <b>Size:</b> 37 KB"}, {"title": "4 - Perotti Daniel Stanley (0001591994) (Reporting)", "filing_url": "https://www.sec.gov/Archives/edgar/data/1591994/000174591625000021/0001745916-25-000021-index.htm", "filing_date": "2025-10-28T21:34:57-04:00", "summary": "<b>Filed:</b> 2025-10-28 <b>AccNo:</b> 0001745916-25-000021 <b>Size:</b> 37 KB"}, {"title": "4 - 325 Capital Master Fund LP (0001972759) (Reporting)", "filing_url": "https://www.sec.gov/Archives/edgar/data/1972759/000092189525002823/0000921895-25-002823-index.htm", "filing_date": "2025-10-28T21:32:46-04:00", "summary": "<b>Filed:</b> 2025-10-28 <b>AccNo:</b> 0000921895-25-002823 <b>Size:</b> 24 KB"}, {"title": "4 - 325 Capital GP, LLC (0001972758) (Reporting)", "filing_url": "https://www.sec.gov/Archives/edgar/data/1972758/000092189525002823/0000921895-25-002823-index.htm", "filing_date": "2025-10-28T21:32:46-04:00", "summary": "<b>Filed:</b> 2025-10-28 <b>AccNo:</b> 0000921895-25-002823 <b>Size:</b> 24 KB"}, {"title": "4 - 325 CAPITAL LLC (0001873893) (Reporting)", "filing_url": "https://www.sec.gov/Archives/edgar/data/1873893/000092189525002823/0000921895-25-002823-index.htm", "filing_date": "2025-10-28T21:32:46-04:00", "summary": "<b>Filed:</b> 2025-10-28 <b>AccNo:</b> 0000921895-25-002823 <b>Size:</b> 24 KB"}, {"title": "4 - MultiSensor AI Holdings, Inc. (0001863990) (Issuer)", "filing_url": "https://www.sec.gov/Archives/edgar/data/1863990/000092189525002823/0000921895-25-002823-index.htm", "filing_date": "2025-10-28T21:32:46-04:00", "summary": "<b>Filed:</b> 2025-10-28 <b>AccNo:</b> 0000921895-25-002823 <b>Size:</b> 24 KB"}, {"title": "4 - FRIEDBERG DANIEL M. (0001448795) (Reporting)", "filing_url": "https://www.sec.gov/Archives/edgar/data/1448795/000092189525002823/0000921895-25-002823-index.htm", "filing_date": "2025-10-28T21:32:46-04:00", "summary": "<b>Filed:</b> 2025-10-28 <b>AccNo:</b> 0000921895-25-002823 <b>Size:</b> 24 KB"}, {"title": "4 - PennyMac Financial Services, Inc. (0001745916) (Issuer)", "filing_url": "https://www.sec.gov/Archives/edgar/data/1745916/000174591625000019/0001745916-25-000019-index.htm", "filing_date": "2025-10-28T21:32:39-04:00", "summary": "<b>Filed:</b> 2025-10-28 <b>AccNo:</b> 0001745916-25-000019 <b>Size:</b> 14 KB"}, {"title": "4 - MCCALLION ANNE (0001232611) (Reporting)", "filing_url": "https://www.sec.gov/Archives/edgar/data/1232611/000174591625000019/0001745916-25-000019-index.htm", "filing_date": "2025-10-28T21:32:39-04:00", "summary": "<b>Filed:</b> 2025-10-28 <b>AccNo:</b> 0001745916-25-000019 <b>Size:</b> 14 KB"}, {"title": "4 - Lynch Catherine A. (0001668396) (Reporting)", "filing_url": "https://www.sec.gov/Archives/edgar/data/1668396/000146442325000008/0001464423-25-000008-index.htm", "filing_date": "2025-10-28T21:29:19-04:00", "summary": "<b>Filed:</b> 2025-10-28 <b>AccNo:</b> 0001464423-25-000008 <b>Size:</b> 6 KB"}, {"title": "4 - PennyMac Mortgage Investment Trust (0001464423) (Issuer)", "filing_url": "https://www.sec.gov/Archives/edgar/data/1464423/000146442325000008/0001464423-25-000008-index.htm", "filing_date": "2025-10-28T21:29:19-04:00", "summary": "<b>Filed:</b> 2025-10-28 <b>AccNo:</b> 0001464423-25-000008 <b>Size:</b> 6 KB"}, {"title": "4 - LINDEMAN JEFFREY G (0001836841) (Reporting)", "filing_url": "https://www.sec.gov/Archives/edgar/data/1836841/000010513225000077/0000105132-25-000077-index.htm", "filing_date": "2025-10-28T21:28:37-04:00", "summary": "<b>Filed:</b> 2025-10-28 <b>AccNo:</b> 0000105132-25-000077 <b>Size:</b> 6 KB"}, {"title": "4 - WD 40 CO (0000105132) (Issuer)", "filing_url": "https://www.sec.gov/Archives/edgar/data/105132/000010513225000077/0000105132-25-000077-index.htm", "filing_date": "2025-10-28T21:28:37-04:00", "summary": "<b>Filed:</b> 2025-10-28 <b>AccNo:</b> 0000105132-25-000077 <b>Size:</b> 6 KB"}, {"title": "4 - KIAMILEV PHENIX Q. (0001896675) (Reporting)", "filing_url": "https://www.sec.gov/Archives/edgar/data/1896675/000010513225000075/0000105132-25-000075-index.htm", "filing_date": "2025-10-28T21:27:02-04:00", "summary": "<b>Filed:</b> 2025-10-28 <b>AccNo:</b> 0000105132-25-000075 <b>Size:</b> 6 KB"}, {"title": "4 - WD 40 CO (0000105132) (Issuer)", "filing_url": "https://www.sec.gov/Archives/edgar/data/105132/000010513225000075/0000105132-25-000075-index.htm", "filing_date": "2025-10-28T21:27:02-04:00", "summary": "<b>Filed:</b> 2025-10-28 <b>AccNo:</b> 0000105132-25-000075 <b>Size:</b> 6 KB"}, {"title": "4 - Traghetto Robert (0002046703) (Reporting)", "filing_url": "https://www.sec.gov/Archives/edgar/data/2046703/000149315225019977/0001493152-25-019977-index.htm", "filing_date": "2025-10-28T21:21:39-04:00", "summary": "<b>Filed:</b> 2025-10-28 <b>AccNo:</b> 0001493152-25-019977 <b>Size:</b> 8 KB"}, {"title": "4 - Fusemachines Inc. (0002033383) (Issuer)", "filing_url": "https://www.sec.gov/Archives/edgar/data/2033383/000149315225019977/0001493152-25-019977-index.htm", "filing_date": "2025-10-28T21:21:39-04:00", "summary": "<b>Filed:</b> 2025-10-28 <b>AccNo:</b> 0001493152-25-019977 <b>Size:</b> 8 KB"}, {"title": "4 - Shrestha Parag (0002046752) (Reporting)", "filing_url": "https://www.sec.gov/Archives/edgar/data/2046752/000149315225019976/0001493152-25-019976-index.htm", "filing_date": "2025-10-28T21:20:30-04:00", "summary": "<b>Filed:</b> 2025-10-28 <b>AccNo:</b> 0001493152-25-019976 <b>Size:</b> 10 KB"}, {"title": "4 - Fusemachines Inc. (0002033383) (Issuer)", "filing_url": "https://www.sec.gov/Archives/edgar/data/2033383/000149315225019976/0001493152-25-019976-index.htm", "filing_date": "2025-10-28T21:20:30-04:00", "summary": "<b>Filed:</b> 2025-10-28 <b>AccNo:</b> 0001493152-25-019976 <b>Size:</b> 10 KB"}, {"title": "4 - Fusemachines Inc. (0002033383) (Issuer)", "filing_url": "https://www.sec.gov/Archives/edgar/data/2033383/000149315225019975/0001493152-25-019975-index.htm", "filing_date": "2025-10-28T21:19:24-04:00", "summary": "<b>Filed:</b> 2025-10-28 <b>AccNo:</b> 0001493152-25-019975 <b>Size:</b> 8 KB"}, {"title": "4 - Shrestha Sanjay K (0001775802) (Reporting)", "filing_url": "https://www.sec.gov/Archives/edgar/data/1775802/000149315225019975/0001493152-25-019975-index.htm", "filing_date": "2025-10-28T21:19:24-04:00", "summary": "<b>Filed:</b> 2025-10-28 <b>AccNo:</b> 0001493152-25-019975 <b>Size:</b> 8 KB"}, {"title": "4 - Maskey Sameer (0002046842) (Reporting)", "filing_url": "https://www.sec.gov/Archives/edgar/data/2046842/000149315225019974/0001493152-25-019974-index.htm", "filing_date": "2025-10-28T21:18:32-04:00", "summary": "<b>Filed:</b> 2025-10-28 <b>AccNo:</b> 0001493152-25-019974 <b>Size:</b> 11 KB"}, {"title": "4 - Fusemachines Inc. (0002033383) (Issuer)", "filing_url": "https://www.sec.gov/Archives/edgar/data/2033383/000149315225019974/0001493152-25-019974-index.htm", "filing_date": "2025-10-28T21:18:32-04:00", "summary": "<b>Filed:</b> 2025-10-28 <b>AccNo:</b> 0001493152-25-019974 <b>Size:</b> 11 KB"}, {"title": "4 - Joshi Anish (0002046749) (Reporting)", "filing_url": "https://www.sec.gov/Archives/edgar/data/2046749/000149315225019973/0001493152-25-019973-index.htm", "filing_date": "2025-10-28T21:17:33-04:00", "summary": "<b>Filed:</b> 2025-10-28 <b>AccNo:</b> 0001493152-25-019973 <b>Size:</b> 10 KB"}, {"title": "4 - Fusemachines Inc. (0002033383) (Issuer)", "filing_url": "https://www.sec.gov/Archives/edgar/data/2033383/000149315225019973/0001493152-25-019973-index.htm", "filing_date": "2025-10-28T21:17:33-04:00", "summary": "<b>Filed:</b> 2025-10-28 <b>AccNo:</b> 0001493152-25-019973 <b>Size:</b> 10 KB"}, {"title": "4 - Gocher Timothy Edward (0002046452) (Reporting)", "filing_url": "https://www.sec.gov/Archives/edgar/data/2046452/000149315225019972/0001493152-25-019972-index.htm", "filing_date": "2025-10-28T21:16:08-04:00", "summary": "<b>Filed:</b> 2025-10-28 <b>AccNo:</b> 0001493152-25-019972 <b>Size:</b> 8 KB"}, {"title": "4 - Fusemachines Inc. (0002033383) (Issuer)", "filing_url": "https://www.sec.gov/Archives/edgar/data/2033383/000149315225019972/0001493152-25-019972-index.htm", "filing_date": "2025-10-28T21:16:08-04:00", "summary": "<b>Filed:</b> 2025-10-28 <b>AccNo:</b> 0001493152-25-019972 <b>Size:</b> 8 KB"}, {"title": "4 - Sionna Therapeutics, Inc. (0002036042) (Issuer)", "filing_url": "https://www.sec.gov/Archives/edgar/data/2036042/000123191925000364/0001231919-25-000364-index.htm", "filing_date": "2025-10-28T21:05:46-04:00", "summary": "<b>Filed:</b> 2025-10-28 <b>AccNo:</b> 0001231919-25-000364 <b>Size:</b> 26 KB"}, {"title": "4 - RA Capital Nexus Fund III, L.P. (0001883840) (Reporting)", "filing_url": "https://www.sec.gov/Archives/edgar/data/1883840/000123191925000364/0001231919-25-000364-index.htm", "filing_date": "2025-10-28T21:05:46-04:00", "summary": "<b>Filed:</b> 2025-10-28 <b>AccNo:</b> 0001231919-25-000364 <b>Size:</b> 26 KB"}, {"title": "4 - RA Capital Nexus Fund, L.P. (0001780117) (Reporting)", "filing_url": "https://www.sec.gov/Archives/edgar/data/1780117/000123191925000364/0001231919-25-000364-index.htm", "filing_date": "2025-10-28T21:05:46-04:00", "summary": "<b>Filed:</b> 2025-10-28 <b>AccNo:</b> 0001231919-25-000364 <b>Size:</b> 26 KB"}, {"title": "4 - Shah Rajeev M. (0001619841) (Reporting)", "filing_url": "https://www.sec.gov/Archives/edgar/data/1619841/000123191925000364/0001231919-25-000364-index.htm", "filing_date": "2025-10-28T21:05:46-04:00", "summary": "<b>Filed:</b> 2025-10-28 <b>AccNo:</b> 0001231919-25-000364 <b>Size:</b> 26 KB"}, {"title": "4 - Kolchinsky Peter (0001384859) (Reporting)", "filing_url": "https://www.sec.gov/Archives/edgar/data/1384859/000123191925000364/0001231919-25-000364-index.htm", "filing_date": "2025-10-28T21:05:46-04:00", "summary": "<b>Filed:</b> 2025-10-28 <b>AccNo:</b> 0001231919-25-000364 <b>Size:</b> 26 KB"}, {"title": "4 - RA CAPITAL MANAGEMENT, L.P. (0001346824) (Reporting)", "filing_url": "https://www.sec.gov/Archives/edgar/data/1346824/000123191925000364/0001231919-25-000364-index.htm", "filing_date": "2025-10-28T21:05:46-04:00", "summary": "<b>Filed:</b> 2025-10-28 <b>AccNo:</b> 0001231919-25-000364 <b>Size:</b> 26 KB"}, {"title": "4 - RA Capital Healthcare Fund LP (0001315082) (Reporting)", "filing_url": "https://www.sec.gov/Archives/edgar/data/1315082/000123191925000364/0001231919-25-000364-index.htm", "filing_date": "2025-10-28T21:05:46-04:00", "summary": "<b>Filed:</b> 2025-10-28 <b>AccNo:</b> 0001231919-25-000364 <b>Size:</b> 26 KB"}, {"title": "4 - QuantumScape Corp (0001811414) (Issuer)", "filing_url": "https://www.sec.gov/Archives/edgar/data/1811414/000117726425000013/0001177264-25-000013-index.htm", "filing_date": "2025-10-28T21:01:02-04:00", "summary": "<b>Filed:</b> 2025-10-28 <b>AccNo:</b> 0001177264-25-000013 <b>Size:</b> 9 KB"}, {"title": "4 - MCCARTHY MICHAEL O III (0001177264) (Reporting)", "filing_url": "https://www.sec.gov/Archives/edgar/data/1177264/000117726425000013/0001177264-25-000013-index.htm", "filing_date": "2025-10-28T21:01:02-04:00", "summary": "<b>Filed:</b> 2025-10-28 <b>AccNo:</b> 0001177264-25-000013 <b>Size:</b> 9 KB"}]