[{"title": "4 - DICKERSON GARY E (0001183258) (Reporting)", "filing_url": "https://www.sec.gov/Archives/edgar/data/1183258/000162828025046877/0001628280-25-046877-index.htm", "filing_date": "2025-10-28T18:56:05-04:00", "summary": "<b>Filed:</b> 2025-10-28 <b>AccNo:</b> 0001628280-25-046877 <b>Size:</b> 7 KB"}, {"title": "4 - APPLIED MATERIALS INC /DE (0000006951) (Issuer)", "filing_url": "https://www.sec.gov/Archives/edgar/data/6951/000162828025046877/0001628280-25-046877-index.htm", "filing_date": "2025-10-28T18:56:05-04:00", "summary": "<b>Filed:</b> 2025-10-28 <b>AccNo:</b> 0001628280-25-046877 <b>Size:</b> 7 KB"}, {"title": "4 - Raja Prabu G. (0001721738) (Reporting)", "filing_url": "https://www.sec.gov/Archives/edgar/data/1721738/000162828025046876/0001628280-25-046876-index.htm", "filing_date": "2025-10-28T18:55:57-04:00", "summary": "<b>Filed:</b> 2025-10-28 <b>AccNo:</b> 0001628280-25-046876 <b>Size:</b> 8 KB"}, {"title": "4 - APPLIED MATERIALS INC /DE (0000006951) (Issuer)", "filing_url": "https://www.sec.gov/Archives/edgar/data/6951/000162828025046876/0001628280-25-046876-index.htm", "filing_date": "2025-10-28T18:55:57-04:00", "summary": "<b>Filed:</b> 2025-10-28 <b>AccNo:</b> 0001628280-25-046876 <b>Size:</b> 8 KB"}, {"title": "4 - Janedis John (0001902269) (Reporting)", "filing_url": "https://www.sec.gov/Archives/edgar/data/1902269/000149315225019935/0001493152-25-019935-index.htm", "filing_date": "2025-10-28T18:54:01-04:00", "summary": "<b>Filed:</b> 2025-10-28 <b>AccNo:</b> 0001493152-25-019935 <b>Size:</b> 5 KB"}, {"title": "4 - fuboTV Inc. /FL (0001484769) (Issuer)", "filing_url": "https://www.sec.gov/Archives/edgar/data/1484769/000149315225019935/0001493152-25-019935-index.htm", "filing_date": "2025-10-28T18:54:01-04:00", "summary": "<b>Filed:</b> 2025-10-28 <b>AccNo:</b> 0001493152-25-019935 <b>Size:</b> 5 KB"}, {"title": "4 - Gandler David (0001808064) (Reporting)", "filing_url": "https://www.sec.gov/Archives/edgar/data/1808064/000149315225019933/0001493152-25-019933-index.htm", "filing_date": "2025-10-28T18:50:46-04:00", "summary": "<b>Filed:</b> 2025-10-28 <b>AccNo:</b> 0001493152-25-019933 <b>Size:</b> 5 KB"}, {"title": "4 - fuboTV Inc. /FL (0001484769) (Issuer)", "filing_url": "https://www.sec.gov/Archives/edgar/data/1484769/000149315225019933/0001493152-25-019933-index.htm", "filing_date": "2025-10-28T18:50:46-04:00", "summary": "<b>Filed:</b> 2025-10-28 <b>AccNo:</b> 0001493152-25-019933 <b>Size:</b> 5 KB"}, {"title": "4 - Alignment Healthcare, Inc. (0001832466) (Issuer)", "filing_url": "https://www.sec.gov/Archives/edgar/data/1832466/000162828025046874/0001628280-25-046874-index.htm", "filing_date": "2025-10-28T18:48:40-04:00", "summary": "<b>Filed:</b> 2025-10-28 <b>AccNo:</b> 0001628280-25-046874 <b>Size:</b> 4 KB"}, {"title": "4 - KONOWIECKI JOSEPH S (0001209523) (Reporting)", "filing_url": "https://www.sec.gov/Archives/edgar/data/1209523/000162828025046874/0001628280-25-046874-index.htm", "filing_date": "2025-10-28T18:48:40-04:00", "summary": "<b>Filed:</b> 2025-10-28 <b>AccNo:</b> 0001628280-25-046874 <b>Size:</b> 4 KB"}, {"title": "4 - BEYOND MEAT, INC. (0001655210) (Issuer)", "filing_url": "https://www.sec.gov/Archives/edgar/data/1655210/000162826425000007/0001628264-25-000007-index.htm", "filing_date": "2025-10-28T18:46:03-04:00", "summary": "<b>Filed:</b> 2025-10-28 <b>AccNo:</b> 0001628264-25-000007 <b>Size:</b> 4 KB"}, {"title": "4 - GRAYSON CHELSEA A (0001628264) (Reporting)", "filing_url": "https://www.sec.gov/Archives/edgar/data/1628264/000162826425000007/0001628264-25-000007-index.htm", "filing_date": "2025-10-28T18:46:03-04:00", "summary": "<b>Filed:</b> 2025-10-28 <b>AccNo:</b> 0001628264-25-000007 <b>Size:</b> 4 KB"}, {"title": "4 - Voss Value Master Fund, LP (0001969435) (Reporting)", "filing_url": "https://www.sec.gov/Archives/edgar/data/1969435/000092189525002819/0000921895-25-002819-index.htm", "filing_date": "2025-10-28T18:45:45-04:00", "summary": "<b>Filed:</b> 2025-10-28 <b>AccNo:</b> 0000921895-25-002819 <b>Size:</b> 20 KB"}, {"title": "4 - Voss Value-Oriented Special Situations Fund, LP (0001863498) (Reporting)", "filing_url": "https://www.sec.gov/Archives/edgar/data/1863498/000092189525002819/0000921895-25-002819-index.htm", "filing_date": "2025-10-28T18:45:45-04:00", "summary": "<b>Filed:</b> 2025-10-28 <b>AccNo:</b> 0000921895-25-002819 <b>Size:</b> 20 KB"}, {"title": "4 - Cocke Travis W. (0001798383) (Reporting)", "filing_url": "https://www.sec.gov/Archives/edgar/data/1798383/000092189525002819/0000921895-25-002819-index.htm", "filing_date": "2025-10-28T18:45:45-04:00", "summary": "<b>Filed:</b> 2025-10-28 <b>AccNo:</b> 0000921895-25-002819 <b>Size:</b> 20 KB"}, {"title": "4 - Voss Advisors GP, LLC (0001798309) (Reporting)", "filing_url": "https://www.sec.gov/Archives/edgar/data/1798309/000092189525002819/0000921895-25-002819-index.htm", "filing_date": "2025-10-28T18:45:45-04:00", "summary": "<b>Filed:</b> 2025-10-28 <b>AccNo:</b> 0000921895-25-002819 <b>Size:</b> 20 KB"}, {"title": "4 - Voss Capital, LP (0001730145) (Reporting)", "filing_url": "https://www.sec.gov/Archives/edgar/data/1730145/000092189525002819/0000921895-25-002819-index.htm", "filing_date": "2025-10-28T18:45:45-04:00", "summary": "<b>Filed:</b> 2025-10-28 <b>AccNo:</b> 0000921895-25-002819 <b>Size:</b> 20 KB"}, {"title": "4 - Rein Therapeutics, Inc. (0001420565) (Issuer)", "filing_url": "https://www.sec.gov/Archives/edgar/data/1420565/000092189525002819/0000921895-25-002819-index.htm", "filing_date": "2025-10-28T18:45:45-04:00", "summary": "<b>Filed:</b> 2025-10-28 <b>AccNo:</b> 0000921895-25-002819 <b>Size:</b> 20 KB"}, {"title": "4 - Tourmaline Bio, Inc. (0001827506) (Issuer)", "filing_url": "https://www.sec.gov/Archives/edgar/data/1827506/000116749625000005/0001167496-25-000005-index.htm", "filing_date": "2025-10-28T18:30:25-04:00", "summary": "<b>Filed:</b> 2025-10-28 <b>AccNo:</b> 0001167496-25-000005 <b>Size:</b> 11 KB"}, {"title": "4 - SIEGALL CLAY B (0001167496) (Reporting)", "filing_url": "https://www.sec.gov/Archives/edgar/data/1167496/000116749625000005/0001167496-25-000005-index.htm", "filing_date": "2025-10-28T18:30:25-04:00", "summary": "<b>Filed:</b> 2025-10-28 <b>AccNo:</b> 0001167496-25-000005 <b>Size:</b> 11 KB"}, {"title": "4 - Thiara Parvinder (0001995535) (Reporting)", "filing_url": "https://www.sec.gov/Archives/edgar/data/1995535/000199553525000003/0001995535-25-000003-index.htm", "filing_date": "2025-10-28T18:30:23-04:00", "summary": "<b>Filed:</b> 2025-10-28 <b>AccNo:</b> 0001995535-25-000003 <b>Size:</b> 12 KB"}, {"title": "4 - Tourmaline Bio, Inc. (0001827506) (Issuer)", "filing_url": "https://www.sec.gov/Archives/edgar/data/1827506/000199553525000003/0001995535-25-000003-index.htm", "filing_date": "2025-10-28T18:30:23-04:00", "summary": "<b>Filed:</b> 2025-10-28 <b>AccNo:</b> 0001995535-25-000003 <b>Size:</b> 12 KB"}, {"title": "4 - Tourmaline Bio, Inc. (0001827506) (Issuer)", "filing_url": "https://www.sec.gov/Archives/edgar/data/1827506/000156922625000005/0001569226-25-000005-index.htm", "filing_date": "2025-10-28T18:30:21-04:00", "summary": "<b>Filed:</b> 2025-10-28 <b>AccNo:</b> 0001569226-25-000005 <b>Size:</b> 12 KB"}, {"title": "4 - Srivastava Sapna (0001569226) (Reporting)", "filing_url": "https://www.sec.gov/Archives/edgar/data/1569226/000156922625000005/0001569226-25-000005-index.htm", "filing_date": "2025-10-28T18:30:21-04:00", "summary": "<b>Filed:</b> 2025-10-28 <b>AccNo:</b> 0001569226-25-000005 <b>Size:</b> 12 KB"}, {"title": "4 - Tourmaline Bio, Inc. (0001827506) (Issuer)", "filing_url": "https://www.sec.gov/Archives/edgar/data/1827506/000124212625000005/0001242126-25-000005-index.htm", "filing_date": "2025-10-28T18:30:19-04:00", "summary": "<b>Filed:</b> 2025-10-28 <b>AccNo:</b> 0001242126-25-000005 <b>Size:</b> 19 KB"}, {"title": "4 - MCDADE MARK (0001242126) (Reporting)", "filing_url": "https://www.sec.gov/Archives/edgar/data/1242126/000124212625000005/0001242126-25-000005-index.htm", "filing_date": "2025-10-28T18:30:19-04:00", "summary": "<b>Filed:</b> 2025-10-28 <b>AccNo:</b> 0001242126-25-000005 <b>Size:</b> 19 KB"}, {"title": "4 - KANTOFF AARON (0001862734) (Reporting)", "filing_url": "https://www.sec.gov/Archives/edgar/data/1862734/000186273425000006/0001862734-25-000006-index.htm", "filing_date": "2025-10-28T18:30:17-04:00", "summary": "<b>Filed:</b> 2025-10-28 <b>AccNo:</b> 0001862734-25-000006 <b>Size:</b> 10 KB"}, {"title": "4 - Tourmaline Bio, Inc. (0001827506) (Issuer)", "filing_url": "https://www.sec.gov/Archives/edgar/data/1827506/000186273425000006/0001862734-25-000006-index.htm", "filing_date": "2025-10-28T18:30:17-04:00", "summary": "<b>Filed:</b> 2025-10-28 <b>AccNo:</b> 0001862734-25-000006 <b>Size:</b> 10 KB"}, {"title": "4 - Tourmaline Bio, Inc. (0001827506) (Issuer)", "filing_url": "https://www.sec.gov/Archives/edgar/data/1827506/000135575825000006/0001355758-25-000006-index.htm", "filing_date": "2025-10-28T18:30:15-04:00", "summary": "<b>Filed:</b> 2025-10-28 <b>AccNo:</b> 0001355758-25-000006 <b>Size:</b> 15 KB"}, {"title": "4 - Castelein Caley (0001355758) (Reporting)", "filing_url": "https://www.sec.gov/Archives/edgar/data/1355758/000135575825000006/0001355758-25-000006-index.htm", "filing_date": "2025-10-28T18:30:15-04:00", "summary": "<b>Filed:</b> 2025-10-28 <b>AccNo:</b> 0001355758-25-000006 <b>Size:</b> 15 KB"}, {"title": "4 - Johnson Kevin Bruce (0001994710) (Reporting)", "filing_url": "https://www.sec.gov/Archives/edgar/data/1994710/000199471025000005/0001994710-25-000005-index.htm", "filing_date": "2025-10-28T18:30:13-04:00", "summary": "<b>Filed:</b> 2025-10-28 <b>AccNo:</b> 0001994710-25-000005 <b>Size:</b> 14 KB"}, {"title": "4 - Tourmaline Bio, Inc. (0001827506) (Issuer)", "filing_url": "https://www.sec.gov/Archives/edgar/data/1827506/000199471025000005/0001994710-25-000005-index.htm", "filing_date": "2025-10-28T18:30:13-04:00", "summary": "<b>Filed:</b> 2025-10-28 <b>AccNo:</b> 0001994710-25-000005 <b>Size:</b> 14 KB"}, {"title": "4 - Jones Susan Dana (0001995339) (Reporting)", "filing_url": "https://www.sec.gov/Archives/edgar/data/1995339/000199533925000003/0001995339-25-000003-index.htm", "filing_date": "2025-10-28T18:30:11-04:00", "summary": "<b>Filed:</b> 2025-10-28 <b>AccNo:</b> 0001995339-25-000003 <b>Size:</b> 14 KB"}, {"title": "4 - Tourmaline Bio, Inc. (0001827506) (Issuer)", "filing_url": "https://www.sec.gov/Archives/edgar/data/1827506/000199533925000003/0001995339-25-000003-index.htm", "filing_date": "2025-10-28T18:30:11-04:00", "summary": "<b>Filed:</b> 2025-10-28 <b>AccNo:</b> 0001995339-25-000003 <b>Size:</b> 14 KB"}, {"title": "4 - Tourmaline Bio, Inc. (0001827506) (Issuer)", "filing_url": "https://www.sec.gov/Archives/edgar/data/1827506/000121450125000004/0001214501-25-000004-index.htm", "filing_date": "2025-10-28T18:30:09-04:00", "summary": "<b>Filed:</b> 2025-10-28 <b>AccNo:</b> 0001214501-25-000004 <b>Size:</b> 14 KB"}, {"title": "4 - MIDDLEKAUFF W BRADFORD (0001214501) (Reporting)", "filing_url": "https://www.sec.gov/Archives/edgar/data/1214501/000121450125000004/0001214501-25-000004-index.htm", "filing_date": "2025-10-28T18:30:09-04:00", "summary": "<b>Filed:</b> 2025-10-28 <b>AccNo:</b> 0001214501-25-000004 <b>Size:</b> 14 KB"}, {"title": "4 - Robinson Ryan F. (0001997834) (Reporting)", "filing_url": "https://www.sec.gov/Archives/edgar/data/1997834/000199783425000006/0001997834-25-000006-index.htm", "filing_date": "2025-10-28T18:30:07-04:00", "summary": "<b>Filed:</b> 2025-10-28 <b>AccNo:</b> 0001997834-25-000006 <b>Size:</b> 15 KB"}, {"title": "4 - Tourmaline Bio, Inc. (0001827506) (Issuer)", "filing_url": "https://www.sec.gov/Archives/edgar/data/1827506/000199783425000006/0001997834-25-000006-index.htm", "filing_date": "2025-10-28T18:30:07-04:00", "summary": "<b>Filed:</b> 2025-10-28 <b>AccNo:</b> 0001997834-25-000006 <b>Size:</b> 15 KB"}, {"title": "4 - Kulkarni Sandeep Chidambar (0001945691) (Reporting)", "filing_url": "https://www.sec.gov/Archives/edgar/data/1945691/000194569125000006/0001945691-25-000006-index.htm", "filing_date": "2025-10-28T18:30:05-04:00", "summary": "<b>Filed:</b> 2025-10-28 <b>AccNo:</b> 0001945691-25-000006 <b>Size:</b> 16 KB"}, {"title": "4 - Tourmaline Bio, Inc. (0001827506) (Issuer)", "filing_url": "https://www.sec.gov/Archives/edgar/data/1827506/000194569125000006/0001945691-25-000006-index.htm", "filing_date": "2025-10-28T18:30:05-04:00", "summary": "<b>Filed:</b> 2025-10-28 <b>AccNo:</b> 0001945691-25-000006 <b>Size:</b> 16 KB"}, {"title": "4 - KINDER MORGAN, INC. (0001506307) (Issuer)", "filing_url": "https://www.sec.gov/Archives/edgar/data/1506307/000150630725000067/0001506307-25-000067-index.htm", "filing_date": "2025-10-28T18:28:02-04:00", "summary": "<b>Filed:</b> 2025-10-28 <b>AccNo:</b> 0001506307-25-000067 <b>Size:</b> 6 KB"}, {"title": "4 - KINDER RICHARD D (0001031190) (Reporting)", "filing_url": "https://www.sec.gov/Archives/edgar/data/1031190/000150630725000067/0001506307-25-000067-index.htm", "filing_date": "2025-10-28T18:28:02-04:00", "summary": "<b>Filed:</b> 2025-10-28 <b>AccNo:</b> 0001506307-25-000067 <b>Size:</b> 6 KB"}, {"title": "4 - Mathew Dennis (0001946788) (Reporting)", "filing_url": "https://www.sec.gov/Archives/edgar/data/1946788/000094787125000931/0000947871-25-000931-index.htm", "filing_date": "2025-10-28T18:23:18-04:00", "summary": "<b>Filed:</b> 2025-10-28 <b>AccNo:</b> 0000947871-25-000931 <b>Size:</b> 4 KB"}, {"title": "4 - Altice USA, Inc. (0001702780) (Issuer)", "filing_url": "https://www.sec.gov/Archives/edgar/data/1702780/000094787125000931/0000947871-25-000931-index.htm", "filing_date": "2025-10-28T18:23:18-04:00", "summary": "<b>Filed:</b> 2025-10-28 <b>AccNo:</b> 0000947871-25-000931 <b>Size:</b> 4 KB"}, {"title": "4 - Volk David J. (0001733127) (Reporting)", "filing_url": "https://www.sec.gov/Archives/edgar/data/1733127/000173312725000005/0001733127-25-000005-index.htm", "filing_date": "2025-10-28T18:21:29-04:00", "summary": "<b>Filed:</b> 2025-10-28 <b>AccNo:</b> 0001733127-25-000005 <b>Size:</b> 7 KB"}, {"title": "4 - Bridgewater Bancshares Inc (0001341317) (Issuer)", "filing_url": "https://www.sec.gov/Archives/edgar/data/1341317/000173312725000005/0001733127-25-000005-index.htm", "filing_date": "2025-10-28T18:21:29-04:00", "summary": "<b>Filed:</b> 2025-10-28 <b>AccNo:</b> 0001733127-25-000005 <b>Size:</b> 7 KB"}, {"title": "4 - O'Dowd William IV (0001520776) (Reporting)", "filing_url": "https://www.sec.gov/Archives/edgar/data/1520776/000107997325001652/0001079973-25-001652-index.htm", "filing_date": "2025-10-28T18:18:32-04:00", "summary": "<b>Filed:</b> 2025-10-28 <b>AccNo:</b> 0001079973-25-001652 <b>Size:</b> 7 KB"}, {"title": "4 - Dolphin Entertainment, Inc. (0001282224) (Issuer)", "filing_url": "https://www.sec.gov/Archives/edgar/data/1282224/000107997325001652/0001079973-25-001652-index.htm", "filing_date": "2025-10-28T18:18:32-04:00", "summary": "<b>Filed:</b> 2025-10-28 <b>AccNo:</b> 0001079973-25-001652 <b>Size:</b> 7 KB"}, {"title": "4 - Brass Steven A (0001691913) (Reporting)", "filing_url": "https://www.sec.gov/Archives/edgar/data/1691913/000010513225000071/0000105132-25-000071-index.htm", "filing_date": "2025-10-28T18:17:22-04:00", "summary": "<b>Filed:</b> 2025-10-28 <b>AccNo:</b> 0000105132-25-000071 <b>Size:</b> 6 KB"}, {"title": "4 - WD 40 CO (0000105132) (Issuer)", "filing_url": "https://www.sec.gov/Archives/edgar/data/105132/000010513225000071/0000105132-25-000071-index.htm", "filing_date": "2025-10-28T18:17:22-04:00", "summary": "<b>Filed:</b> 2025-10-28 <b>AccNo:</b> 0000105132-25-000071 <b>Size:</b> 6 KB"}]